{"/39":[{"key":"css","val":[{"selector":".ready","props":{"background-color":"lightblue","color":"black"}},{"selector":".noclick","props":{"user-select":"none","pointer-events":"none"}}]},{"key":"html","val":[{"parent":"forms","id":"UI","new":"div","style":{"position":"absolute","float":"left","width":"200px"}},{"parent":"UI","id":"playbutton","new":"button","text":"play","class":"button","style":{"float":"left"},"onclick":"if( !this.classList.contains('ready') )\n            {\n                this.classList.add('ready');\n                drawsocket.input({\n                    key: 'tween',\n                    val: [ {\n                        id: 'score-anim',\n                        cmd : 'play'\n                    }, {\n                        id: 'miniscore-anim',\n                        cmd : 'play'\n                    } ],\n                    timetag: Date.now()\n                });\n            } else {\n                this.classList.remove('ready');\n                let starttime = document.getElementById('userinput');\n                drawsocket.input({\n                    key: 'tween',\n                    val: [{\n                        id: 'score-anim',\n                        cmd: 'pause',\n                        time: starttime.value\n                    }, {\n                        id: 'miniscore-anim',\n                        cmd : 'pause',\n                        time: starttime.value\n                    }]\n                });\n            }"},{"parent":"UI","new":"label","for":"userinput","id":"sent","name":"sent","text":"start at time<br>","style":{"font-size":"60%","color":"gray","margin-left":"20px"}},{"parent":"UI","new":"input","type":"text","id":"userinput","name":"userinput","placeholder":"0","size":5,"onkeydown":"\n     if( drawsocket.submitOnEnterKey(this) ) { \n       let button = document.getElementById('playbutton');\n       if( button.classList.contains('ready') )\n            button.classList.remove('ready');\n\n       drawsocket.input({\n         key: 'tween',\n         val: [{\n           id: 'score-anim',\n           cmd: 'pause',\n           time: this.value\n         }, {\n          id: 'miniscore-anim',\n       \t\t cmd : 'pause',\n          time: this.value\n          }]\n       });\n     }","style":{"margin-left":"35px","text-align":"center"}}]},{"key":"svg","val":[{"new":"g","parent":"defs","id":"defscore","transform":"scale(1.5)","child":[{"parent":"main-svg","new":"g","id":"back"},{"parent":"main-svg","new":"g","id":"main"},{"parent":"main-svg","new":"g","id":"overlay"},{"parent":"main","new":"text","id":"_1435","x":0,"y":0,"child":"4.3 Flute","style":{"fill":"rgb(0,0,0)","font-family":"Arial","font-size":10},"transform":"matrix(1,0,0,1,-9.693359375,68)"},{"parent":"main","new":"path","id":"_1436","d":"M583.5999755859375,84 L593.4000244140625,84","style":{"stroke-width":0.4},"transform":"matrix(1,0,0,1,0,0)"},{"parent":"main","new":"text","id":"_1437","x":0,"y":0,"child":"","style":{"fill":"rgb(0,0,0)","font-family":"Bravura","font-size":22},"transform":"matrix(1,0,0,1,585,84)"},{"parent":"main","new":"text","id":"_1438","x":0,"y":0,"child":"","style":{"fill":"rgb(0,0,0)","font-family":"Bravura","font-size":24},"transform":"matrix(1,0,0,1,582,99)"},{"parent":"main","new":"path","id":"_1439","d":"M5,3 L106.636367,3","style":{"stroke-width":2,"stroke":"rgb(0,0,255)","fill":"none"},"transform":"matrix(1,0,0,1,587,81)"},{"parent":"main","new":"path","id":"_1440","d":"M106.636367,1 L106.636367,5","style":{"stroke":"rgb(0,0,255)","fill":"none"},"transform":"matrix(1,0,0,1,587,81)"},{"parent":"main","new":"text","id":"_1441","x":0,"y":0,"child":"","style":{"fill":"rgb(0,0,0)","font-family":"Bravura","font-size":22},"transform":"matrix(1,0,0,1,783,75)"},{"parent":"main","new":"path","id":"_1442","d":"M5,3 L106.636367,3","style":{"stroke-width":2,"stroke":"rgb(0,0,255)","fill":"none"},"transform":"matrix(1,0,0,1,785,72)"},{"parent":"main","new":"path","id":"_1443","d":"M106.636367,1 L106.636367,5","style":{"stroke":"rgb(0,0,255)","fill":"none"},"transform":"matrix(1,0,0,1,785,72)"},{"parent":"main","new":"path","id":"_1444","d":"M972.5999755859375,84 L982.4000244140625,84","style":{"stroke-width":0.4},"transform":"matrix(1,0,0,1,0,0)"},{"parent":"main","new":"path","id":"_1445","d":"M972.5999755859375,90 L982.4000244140625,90","style":{"stroke-width":0.4},"transform":"matrix(1,0,0,1,0,0)"},{"parent":"main","new":"text","id":"_1446","x":0,"y":0,"child":"","style":{"fill":"rgb(0,0,0)","font-family":"Bravura","font-size":22},"transform":"matrix(1,0,0,1,974,90)"},{"parent":"main","new":"text","id":"_1447","x":0,"y":0,"child":"","style":{"fill":"rgb(0,0,0)","font-family":"Bravura","font-size":24},"transform":"matrix(1,0,0,1,966.5555419921875,90)"},{"parent":"main","new":"path","id":"_1448","d":"M5,3 L106.636367,3","style":{"stroke-width":2,"stroke":"rgb(0,0,255)","fill":"none"},"transform":"matrix(1,0,0,1,976,87)"},{"parent":"main","new":"path","id":"_1449","d":"M106.636367,1 L106.636367,5","style":{"stroke":"rgb(0,0,255)","fill":"none"},"transform":"matrix(1,0,0,1,976,87)"},{"parent":"main","new":"text","id":"_1450","x":0,"y":0,"child":"","style":{"fill":"rgb(0,0,0)","font-family":"Bravura","font-size":22},"transform":"matrix(1,0,0,1,1170,81)"},{"parent":"main","new":"text","id":"_1451","x":0,"y":0,"child":"","style":{"fill":"rgb(0,0,0)","font-family":"Bravura","font-size":24},"transform":"matrix(1,0,0,1,1162.5555419921875,81)"},{"parent":"main","new":"path","id":"_1452","d":"M5,3 L106.636367,3","style":{"stroke-width":2,"stroke":"rgb(0,0,255)","fill":"none"},"transform":"matrix(1,0,0,1,1172,78)"},{"parent":"main","new":"path","id":"_1453","d":"M106.636367,1 L106.636367,5","style":{"stroke":"rgb(0,0,255)","fill":"none"},"transform":"matrix(1,0,0,1,1172,78)"},{"parent":"main","new":"text","id":"_1454","x":0,"y":0,"child":"","style":{"fill":"rgb(0,0,0)","font-family":"Bravura","font-size":22},"transform":"matrix(1,0,0,1,1483,72)"},{"parent":"main","new":"text","id":"_1455","x":0,"y":0,"child":"","style":{"fill":"rgb(0,0,0)","font-family":"Bravura","font-size":24},"transform":"matrix(1,0,0,1,1475.5555419921875,72)"},{"parent":"main","new":"path","id":"_1456","d":"M5,3 L106.636367,3","style":{"stroke-width":2,"stroke":"rgb(0,0,255)","fill":"none"},"transform":"matrix(1,0,0,1,1485,69)"},{"parent":"main","new":"path","id":"_1457","d":"M106.636367,1 L106.636367,5","style":{"stroke":"rgb(0,0,255)","fill":"none"},"transform":"matrix(1,0,0,1,1485,69)"},{"parent":"main","new":"path","id":"_1458","d":"M1669.5999755859375,84 L1679.4000244140625,84","style":{"stroke-width":0.4},"transform":"matrix(1,0,0,1,0,0)"},{"parent":"main","new":"text","id":"_1459","x":0,"y":0,"child":"","style":{"fill":"rgb(0,0,0)","font-family":"Bravura","font-size":22},"transform":"matrix(1,0,0,1,1671,84)"},{"parent":"main","new":"text","id":"_1460","x":0,"y":0,"child":"","style":{"fill":"rgb(0,0,0)","font-family":"Bravura","font-size":24},"transform":"matrix(1,0,0,1,1663.5555419921875,84)"},{"parent":"main","new":"path","id":"_1461","d":"M5,3 L106.636367,3","style":{"stroke-width":2,"stroke":"rgb(0,0,255)","fill":"none"},"transform":"matrix(1,0,0,1,1673,81)"},{"parent":"main","new":"path","id":"_1462","d":"M106.636367,1 L106.636367,5","style":{"stroke":"rgb(0,0,255)","fill":"none"},"transform":"matrix(1,0,0,1,1673,81)"},{"parent":"main","new":"text","id":"_1463","x":0,"y":0,"child":"","style":{"fill":"rgb(0,0,0)","font-family":"Bravura","font-size":22},"transform":"matrix(1,0,0,1,1963,75)"},{"parent":"main","new":"text","id":"_1464","x":0,"y":0,"child":"","style":{"fill":"rgb(0,0,0)","font-family":"Bravura","font-size":24},"transform":"matrix(1,0,0,1,1955.5555419921875,75)"},{"parent":"main","new":"path","id":"_1465","d":"M5,3 L106.636367,3","style":{"stroke-width":2,"stroke":"rgb(0,0,255)","fill":"none"},"transform":"matrix(1,0,0,1,1965,72)"},{"parent":"main","new":"path","id":"_1466","d":"M106.636367,1 L106.636367,5","style":{"stroke":"rgb(0,0,255)","fill":"none"},"transform":"matrix(1,0,0,1,1965,72)"},{"parent":"main","new":"path","id":"_1467","d":"M2149.60009765625,84 L2159.39990234375,84","style":{"stroke-width":0.4},"transform":"matrix(1,0,0,1,0,0)"},{"parent":"main","new":"text","id":"_1468","x":0,"y":0,"child":"","style":{"fill":"rgb(0,0,0)","font-family":"Bravura","font-size":22},"transform":"matrix(1,0,0,1,2151,87)"},{"parent":"main","new":"path","id":"_1469","d":"M5,3 L106.636367,3","style":{"stroke-width":2,"stroke":"rgb(0,0,255)","fill":"none"},"transform":"matrix(1,0,0,1,2153,84)"},{"parent":"main","new":"path","id":"_1470","d":"M106.636367,1 L106.636367,5","style":{"stroke":"rgb(0,0,255)","fill":"none"},"transform":"matrix(1,0,0,1,2153,84)"},{"parent":"main","new":"text","id":"_1471","x":0,"y":0,"child":"","style":{"fill":"rgb(0,0,0)","font-family":"Bravura","font-size":22},"transform":"matrix(1,0,0,1,2464,78)"},{"parent":"main","new":"path","id":"_1472","d":"M5,3 L106.636367,3","style":{"stroke-width":2,"stroke":"rgb(0,0,255)","fill":"none"},"transform":"matrix(1,0,0,1,2466,75)"},{"parent":"main","new":"path","id":"_1473","d":"M106.636367,1 L106.636367,5","style":{"stroke":"rgb(0,0,255)","fill":"none"},"transform":"matrix(1,0,0,1,2466,75)"},{"parent":"main","new":"text","id":"_1474","x":0,"y":0,"child":"","style":{"fill":"rgb(0,0,0)","font-family":"Bravura","font-size":22},"transform":"matrix(1,0,0,1,2655,69)"},{"parent":"main","new":"path","id":"_1475","d":"M5,3 L106.636367,3","style":{"stroke-width":2,"stroke":"rgb(0,0,255)","fill":"none"},"transform":"matrix(1,0,0,1,2657,66)"},{"parent":"main","new":"path","id":"_1476","d":"M106.636367,1 L106.636367,5","style":{"stroke":"rgb(0,0,255)","fill":"none"},"transform":"matrix(1,0,0,1,2657,66)"},{"parent":"main","new":"text","id":"_1477","x":0,"y":0,"child":"","style":{"fill":"rgb(0,0,0)","font-family":"Bravura","font-size":22},"transform":"matrix(1,0,0,1,2838,81)"},{"parent":"main","new":"text","id":"_1478","x":0,"y":0,"child":"","style":{"fill":"rgb(0,0,0)","font-family":"Bravura","font-size":24},"transform":"matrix(1,0,0,1,2833.5556640625,81)"},{"parent":"main","new":"path","id":"_1479","d":"M5,3 L106.636367,3","style":{"stroke-width":2,"stroke":"rgb(0,0,255)","fill":"none"},"transform":"matrix(1,0,0,1,2840,78)"},{"parent":"main","new":"path","id":"_1480","d":"M106.636367,1 L106.636367,5","style":{"stroke":"rgb(0,0,255)","fill":"none"},"transform":"matrix(1,0,0,1,2840,78)"},{"parent":"main","new":"path","id":"_5402","d":"M0,0L100,7.5,0,15","style":{"fill":"none","stroke-width":0.6},"transform":"matrix(22.47,0,0,1,591,108)"},{"parent":"main","new":"text","id":"_5403","x":0,"y":0,"child":"","style":{"fill":"rgb(0,0,0)","font-family":"Bravura","font-size":22},"transform":"matrix(1,0,0,1,3085,75)"},{"parent":"main","new":"text","id":"_5404","x":0,"y":0,"child":"","style":{"fill":"rgb(0,0,0)","font-family":"Bravura","font-size":24},"transform":"matrix(1,0,0,1,3082,96)"},{"parent":"main","new":"path","id":"_5405","d":"M5,3 L118,3","style":{"stroke-width":2,"stroke":"rgb(0,0,255)","fill":"none"},"transform":"matrix(1,0,0,1,3087,72)"},{"parent":"main","new":"path","id":"_5406","d":"M118,1 L118,5","style":{"stroke":"rgb(0,0,255)","fill":"none"},"transform":"matrix(1,0,0,1,3087,72)"},{"parent":"main","new":"path","id":"_5407","d":"M3300.60009765625,84 L3310.39990234375,84","style":{"stroke-width":0.4},"transform":"matrix(1,0,0,1,0,0)"},{"parent":"main","new":"path","id":"_5408","d":"M3300.60009765625,90 L3310.39990234375,90","style":{"stroke-width":0.4},"transform":"matrix(1,0,0,1,0,0)"},{"parent":"main","new":"text","id":"_5409","x":0,"y":0,"child":"","style":{"fill":"rgb(0,0,0)","font-family":"Bravura","font-size":22},"transform":"matrix(1,0,0,1,3302,90)"},{"parent":"main","new":"text","id":"_5410","x":0,"y":0,"child":"","style":{"fill":"rgb(0,0,0)","font-family":"Bravura","font-size":24},"transform":"matrix(1,0,0,1,3294.5556640625,90)"},{"parent":"main","new":"path","id":"_5411","d":"M5,3 L118,3","style":{"stroke-width":2,"stroke":"rgb(0,0,255)","fill":"none"},"transform":"matrix(1,0,0,1,3304,87)"},{"parent":"main","new":"path","id":"_5412","d":"M118,1 L118,5","style":{"stroke":"rgb(0,0,255)","fill":"none"},"transform":"matrix(1,0,0,1,3304,87)"},{"parent":"main","new":"text","id":"_5413","x":0,"y":0,"child":"","style":{"fill":"rgb(0,0,0)","font-family":"Bravura","font-size":22},"transform":"matrix(1,0,0,1,3513,81)"},{"parent":"main","new":"text","id":"_5414","x":0,"y":0,"child":"","style":{"fill":"rgb(0,0,0)","font-family":"Bravura","font-size":24},"transform":"matrix(1,0,0,1,3505.5556640625,81)"},{"parent":"main","new":"path","id":"_5415","d":"M5,3 L118,3","style":{"stroke-width":2,"stroke":"rgb(0,0,255)","fill":"none"},"transform":"matrix(1,0,0,1,3515,78)"},{"parent":"main","new":"path","id":"_5416","d":"M118,1 L118,5","style":{"stroke":"rgb(0,0,255)","fill":"none"},"transform":"matrix(1,0,0,1,3515,78)"},{"parent":"main","new":"text","id":"_5417","x":0,"y":0,"child":"","style":{"fill":"rgb(0,0,0)","font-family":"Bravura","font-size":22},"transform":"matrix(1,0,0,1,3725,72)"},{"parent":"main","new":"text","id":"_5418","x":0,"y":0,"child":"","style":{"fill":"rgb(0,0,0)","font-family":"Bravura","font-size":24},"transform":"matrix(1,0,0,1,3717.5556640625,72)"},{"parent":"main","new":"path","id":"_5419","d":"M5,3 L118,3","style":{"stroke-width":2,"stroke":"rgb(0,0,255)","fill":"none"},"transform":"matrix(1,0,0,1,3727,69)"},{"parent":"main","new":"path","id":"_5420","d":"M118,1 L118,5","style":{"stroke":"rgb(0,0,255)","fill":"none"},"transform":"matrix(1,0,0,1,3727,69)"},{"parent":"main","new":"path","id":"_5421","d":"M4055.60009765625,84 L4065.39990234375,84","style":{"stroke-width":0.4},"transform":"matrix(1,0,0,1,0,0)"},{"parent":"main","new":"text","id":"_5422","x":0,"y":0,"child":"","style":{"fill":"rgb(0,0,0)","font-family":"Bravura","font-size":22},"transform":"matrix(1,0,0,1,4057,84)"},{"parent":"main","new":"text","id":"_5423","x":0,"y":0,"child":"","style":{"fill":"rgb(0,0,0)","font-family":"Bravura","font-size":24},"transform":"matrix(1,0,0,1,4049.5556640625,84)"},{"parent":"main","new":"path","id":"_5424","d":"M5,3 L118,3","style":{"stroke-width":2,"stroke":"rgb(0,0,255)","fill":"none"},"transform":"matrix(1,0,0,1,4059,81)"},{"parent":"main","new":"path","id":"_5425","d":"M118,1 L118,5","style":{"stroke":"rgb(0,0,255)","fill":"none"},"transform":"matrix(1,0,0,1,4059,81)"},{"parent":"main","new":"text","id":"_5426","x":0,"y":0,"child":"","style":{"fill":"rgb(0,0,0)","font-family":"Bravura","font-size":22},"transform":"matrix(1,0,0,1,4317,75)"},{"parent":"main","new":"text","id":"_5427","x":0,"y":0,"child":"","style":{"fill":"rgb(0,0,0)","font-family":"Bravura","font-size":24},"transform":"matrix(1,0,0,1,4309.5556640625,75)"},{"parent":"main","new":"path","id":"_5428","d":"M5,3 L118,3","style":{"stroke-width":2,"stroke":"rgb(0,0,255)","fill":"none"},"transform":"matrix(1,0,0,1,4319,72)"},{"parent":"main","new":"path","id":"_5429","d":"M118,1 L118,5","style":{"stroke":"rgb(0,0,255)","fill":"none"},"transform":"matrix(1,0,0,1,4319,72)"},{"parent":"main","new":"path","id":"_5430","d":"M4575.60009765625,84 L4585.39990234375,84","style":{"stroke-width":0.4},"transform":"matrix(1,0,0,1,0,0)"},{"parent":"main","new":"text","id":"_5431","x":0,"y":0,"child":"","style":{"fill":"rgb(0,0,0)","font-family":"Bravura","font-size":22},"transform":"matrix(1,0,0,1,4577,87)"},{"parent":"main","new":"path","id":"_5432","d":"M5,3 L118,3","style":{"stroke-width":2,"stroke":"rgb(0,0,255)","fill":"none"},"transform":"matrix(1,0,0,1,4579,84)"},{"parent":"main","new":"path","id":"_5433","d":"M118,1 L118,5","style":{"stroke":"rgb(0,0,255)","fill":"none"},"transform":"matrix(1,0,0,1,4579,84)"},{"parent":"main","new":"text","id":"_5434","x":0,"y":0,"child":"","style":{"fill":"rgb(0,0,0)","font-family":"Bravura","font-size":22},"transform":"matrix(1,0,0,1,4909,78)"},{"parent":"main","new":"path","id":"_5435","d":"M5,3 L118,3","style":{"stroke-width":2,"stroke":"rgb(0,0,255)","fill":"none"},"transform":"matrix(1,0,0,1,4911,75)"},{"parent":"main","new":"path","id":"_5436","d":"M118,1 L118,5","style":{"stroke":"rgb(0,0,255)","fill":"none"},"transform":"matrix(1,0,0,1,4911,75)"},{"parent":"main","new":"text","id":"_5437","x":0,"y":0,"child":"","style":{"fill":"rgb(0,0,0)","font-family":"Bravura","font-size":22},"transform":"matrix(1,0,0,1,5118,69)"},{"parent":"main","new":"path","id":"_5438","d":"M5,3 L118,3","style":{"stroke-width":2,"stroke":"rgb(0,0,255)","fill":"none"},"transform":"matrix(1,0,0,1,5120,66)"},{"parent":"main","new":"path","id":"_5439","d":"M118,1 L118,5","style":{"stroke":"rgb(0,0,255)","fill":"none"},"transform":"matrix(1,0,0,1,5120,66)"},{"parent":"main","new":"text","id":"_5440","x":0,"y":0,"child":"","style":{"fill":"rgb(0,0,0)","font-family":"Bravura","font-size":22},"transform":"matrix(1,0,0,1,5320,81)"},{"parent":"main","new":"text","id":"_5441","x":0,"y":0,"child":"","style":{"fill":"rgb(0,0,0)","font-family":"Bravura","font-size":24},"transform":"matrix(1,0,0,1,5315.5556640625,81)"},{"parent":"main","new":"path","id":"_5442","d":"M5,3 L118,3","style":{"stroke-width":2,"stroke":"rgb(0,0,255)","fill":"none"},"transform":"matrix(1,0,0,1,5322,78)"},{"parent":"main","new":"path","id":"_5443","d":"M118,1 L118,5","style":{"stroke":"rgb(0,0,255)","fill":"none"},"transform":"matrix(1,0,0,1,5322,78)"},{"parent":"main","new":"path","id":"_9376","d":"M0,0L100,7.5,0,15","style":{"fill":"none","stroke-width":0.6},"transform":"matrix(22.29,0,0,1,3091,108)"},{"parent":"main","new":"path","id":"_9377","d":"M5583.60009765625,84 L5593.39990234375,84","style":{"stroke-width":0.4},"transform":"matrix(1,0,0,1,0,0)"},{"parent":"main","new":"path","id":"_9378","d":"M5583.60009765625,90 L5593.39990234375,90","style":{"stroke-width":0.4},"transform":"matrix(1,0,0,1,0,0)"},{"parent":"main","new":"text","id":"_9379","x":0,"y":0,"child":"","style":{"fill":"rgb(0,0,0)","font-family":"Bravura","font-size":22},"transform":"matrix(1,0,0,1,5585,90)"},{"parent":"main","new":"text","id":"_9380","x":0,"y":0,"child":"","style":{"fill":"rgb(0,0,0)","font-family":"Bravura","font-size":24},"transform":"matrix(1,0,0,1,5577.5556640625,90)"},{"parent":"main","new":"text","id":"_9381","x":0,"y":0,"child":"","style":{"fill":"rgb(0,0,0)","font-family":"Bravura","font-size":24},"transform":"matrix(1,0,0,1,5582,105)"},{"parent":"main","new":"path","id":"_9382","d":"M5,3 L131.888896,3","style":{"stroke-width":2,"stroke":"rgb(0,0,255)","fill":"none"},"transform":"matrix(1,0,0,1,5587,87)"},{"parent":"main","new":"path","id":"_9383","d":"M131.888896,1 L131.888896,5","style":{"stroke":"rgb(0,0,255)","fill":"none"},"transform":"matrix(1,0,0,1,5587,87)"},{"parent":"main","new":"text","id":"_9384","x":0,"y":0,"child":"","style":{"fill":"rgb(0,0,0)","font-family":"Bravura","font-size":22},"transform":"matrix(1,0,0,1,5823,81)"},{"parent":"main","new":"text","id":"_9385","x":0,"y":0,"child":"","style":{"fill":"rgb(0,0,0)","font-family":"Bravura","font-size":24},"transform":"matrix(1,0,0,1,5815.5556640625,81)"},{"parent":"main","new":"path","id":"_9386","d":"M5,3 L131.888896,3","style":{"stroke-width":2,"stroke":"rgb(0,0,255)","fill":"none"},"transform":"matrix(1,0,0,1,5825,78)"},{"parent":"main","new":"path","id":"_9387","d":"M131.888896,1 L131.888896,5","style":{"stroke":"rgb(0,0,255)","fill":"none"},"transform":"matrix(1,0,0,1,5825,78)"},{"parent":"main","new":"text","id":"_9388","x":0,"y":0,"child":"","style":{"fill":"rgb(0,0,0)","font-family":"Bravura","font-size":22},"transform":"matrix(1,0,0,1,6061,72)"},{"parent":"main","new":"text","id":"_9389","x":0,"y":0,"child":"","style":{"fill":"rgb(0,0,0)","font-family":"Bravura","font-size":24},"transform":"matrix(1,0,0,1,6053.5556640625,72)"},{"parent":"main","new":"path","id":"_9390","d":"M5,3 L131.888896,3","style":{"stroke-width":2,"stroke":"rgb(0,0,255)","fill":"none"},"transform":"matrix(1,0,0,1,6063,69)"},{"parent":"main","new":"path","id":"_9391","d":"M131.888896,1 L131.888896,5","style":{"stroke":"rgb(0,0,255)","fill":"none"},"transform":"matrix(1,0,0,1,6063,69)"},{"parent":"main","new":"path","id":"_9392","d":"M6354.60009765625,84 L6364.39990234375,84","style":{"stroke-width":0.4},"transform":"matrix(1,0,0,1,0,0)"},{"parent":"main","new":"text","id":"_9393","x":0,"y":0,"child":"","style":{"fill":"rgb(0,0,0)","font-family":"Bravura","font-size":22},"transform":"matrix(1,0,0,1,6356,84)"},{"parent":"main","new":"text","id":"_9394","x":0,"y":0,"child":"","style":{"fill":"rgb(0,0,0)","font-family":"Bravura","font-size":24},"transform":"matrix(1,0,0,1,6348.5556640625,84)"},{"parent":"main","new":"path","id":"_9395","d":"M5,3 L131.888896,3","style":{"stroke-width":2,"stroke":"rgb(0,0,255)","fill":"none"},"transform":"matrix(1,0,0,1,6358,81)"},{"parent":"main","new":"path","id":"_9396","d":"M131.888896,1 L131.888896,5","style":{"stroke":"rgb(0,0,255)","fill":"none"},"transform":"matrix(1,0,0,1,6358,81)"},{"parent":"main","new":"text","id":"_9397","x":0,"y":0,"child":"","style":{"fill":"rgb(0,0,0)","font-family":"Bravura","font-size":22},"transform":"matrix(1,0,0,1,6651,75)"},{"parent":"main","new":"text","id":"_9398","x":0,"y":0,"child":"","style":{"fill":"rgb(0,0,0)","font-family":"Bravura","font-size":24},"transform":"matrix(1,0,0,1,6643.5556640625,75)"},{"parent":"main","new":"path","id":"_9399","d":"M5,3 L131.888896,3","style":{"stroke-width":2,"stroke":"rgb(0,0,255)","fill":"none"},"transform":"matrix(1,0,0,1,6653,72)"},{"parent":"main","new":"path","id":"_9400","d":"M131.888896,1 L131.888896,5","style":{"stroke":"rgb(0,0,255)","fill":"none"},"transform":"matrix(1,0,0,1,6653,72)"},{"parent":"main","new":"path","id":"_9401","d":"M6981.60009765625,84 L6991.39990234375,84","style":{"stroke-width":0.4},"transform":"matrix(1,0,0,1,0,0)"},{"parent":"main","new":"text","id":"_9402","x":0,"y":0,"child":"","style":{"fill":"rgb(0,0,0)","font-family":"Bravura","font-size":22},"transform":"matrix(1,0,0,1,6983,87)"},{"parent":"main","new":"path","id":"_9403","d":"M5,3 L131.888896,3","style":{"stroke-width":2,"stroke":"rgb(0,0,255)","fill":"none"},"transform":"matrix(1,0,0,1,6985,84)"},{"parent":"main","new":"path","id":"_9404","d":"M131.888896,1 L131.888896,5","style":{"stroke":"rgb(0,0,255)","fill":"none"},"transform":"matrix(1,0,0,1,6985,84)"},{"parent":"main","new":"text","id":"_9405","x":0,"y":0,"child":"","style":{"fill":"rgb(0,0,0)","font-family":"Bravura","font-size":22},"transform":"matrix(1,0,0,1,7278,78)"},{"parent":"main","new":"path","id":"_9406","d":"M5,3 L131.888896,3","style":{"stroke-width":2,"stroke":"rgb(0,0,255)","fill":"none"},"transform":"matrix(1,0,0,1,7280,75)"},{"parent":"main","new":"path","id":"_9407","d":"M131.888896,1 L131.888896,5","style":{"stroke":"rgb(0,0,255)","fill":"none"},"transform":"matrix(1,0,0,1,7280,75)"},{"parent":"main","new":"text","id":"_9408","x":0,"y":0,"child":"","style":{"fill":"rgb(0,0,0)","font-family":"Bravura","font-size":22},"transform":"matrix(1,0,0,1,7573,69)"},{"parent":"main","new":"path","id":"_9409","d":"M5,3 L131.888896,3","style":{"stroke-width":2,"stroke":"rgb(0,0,255)","fill":"none"},"transform":"matrix(1,0,0,1,7575,66)"},{"parent":"main","new":"path","id":"_9410","d":"M131.888896,1 L131.888896,5","style":{"stroke":"rgb(0,0,255)","fill":"none"},"transform":"matrix(1,0,0,1,7575,66)"},{"parent":"main","new":"text","id":"_9411","x":0,"y":0,"child":"","style":{"fill":"rgb(0,0,0)","font-family":"Bravura","font-size":22},"transform":"matrix(1,0,0,1,7797,81)"},{"parent":"main","new":"text","id":"_9412","x":0,"y":0,"child":"","style":{"fill":"rgb(0,0,0)","font-family":"Bravura","font-size":24},"transform":"matrix(1,0,0,1,7792.5556640625,81)"},{"parent":"main","new":"path","id":"_9413","d":"M5,3 L131.888896,3","style":{"stroke-width":2,"stroke":"rgb(0,0,255)","fill":"none"},"transform":"matrix(1,0,0,1,7799,78)"},{"parent":"main","new":"path","id":"_9414","d":"M131.888896,1 L131.888896,5","style":{"stroke":"rgb(0,0,255)","fill":"none"},"transform":"matrix(1,0,0,1,7799,78)"},{"parent":"main","new":"path","id":"_13318","d":"M0,0L100,7.5,0,15","style":{"fill":"none","stroke-width":0.6},"transform":"matrix(22.06,0,0,1,5591,108)"},{"parent":"main","new":"text","id":"_13319","x":0,"y":0,"child":"","style":{"fill":"rgb(0,0,0)","font-family":"Bravura","font-size":22},"transform":"matrix(1,0,0,1,8085,81)"},{"parent":"main","new":"text","id":"_13320","x":0,"y":0,"child":"","style":{"fill":"rgb(0,0,0)","font-family":"Bravura","font-size":24},"transform":"matrix(1,0,0,1,8077.5556640625,81)"},{"parent":"main","new":"text","id":"_13321","x":0,"y":0,"child":"","style":{"fill":"rgb(0,0,0)","font-family":"Bravura","font-size":24},"transform":"matrix(1,0,0,1,8082,96)"},{"parent":"main","new":"path","id":"_13322","d":"M5,3 L149.25,3","style":{"stroke-width":2,"stroke":"rgb(0,0,255)","fill":"none"},"transform":"matrix(1,0,0,1,8087,78)"},{"parent":"main","new":"path","id":"_13323","d":"M149.25,1 L149.25,5","style":{"stroke":"rgb(0,0,255)","fill":"none"},"transform":"matrix(1,0,0,1,8087,78)"},{"parent":"main","new":"text","id":"_13324","x":0,"y":0,"child":"","style":{"fill":"rgb(0,0,0)","font-family":"Bravura","font-size":22},"transform":"matrix(1,0,0,1,8350,72)"},{"parent":"main","new":"text","id":"_13325","x":0,"y":0,"child":"","style":{"fill":"rgb(0,0,0)","font-family":"Bravura","font-size":24},"transform":"matrix(1,0,0,1,8342.5556640625,72)"},{"parent":"main","new":"path","id":"_13326","d":"M5,3 L149.25,3","style":{"stroke-width":2,"stroke":"rgb(0,0,255)","fill":"none"},"transform":"matrix(1,0,0,1,8352,69)"},{"parent":"main","new":"path","id":"_13327","d":"M149.25,1 L149.25,5","style":{"stroke":"rgb(0,0,255)","fill":"none"},"transform":"matrix(1,0,0,1,8352,69)"},{"parent":"main","new":"path","id":"_13328","d":"M8619.599609375,84 L8629.400390625,84","style":{"stroke-width":0.4},"transform":"matrix(1,0,0,1,0,0)"},{"parent":"main","new":"text","id":"_13329","x":0,"y":0,"child":"","style":{"fill":"rgb(0,0,0)","font-family":"Bravura","font-size":22},"transform":"matrix(1,0,0,1,8621,84)"},{"parent":"main","new":"text","id":"_13330","x":0,"y":0,"child":"","style":{"fill":"rgb(0,0,0)","font-family":"Bravura","font-size":24},"transform":"matrix(1,0,0,1,8613.5556640625,84)"},{"parent":"main","new":"path","id":"_13331","d":"M5,3 L149.25,3","style":{"stroke-width":2,"stroke":"rgb(0,0,255)","fill":"none"},"transform":"matrix(1,0,0,1,8623,81)"},{"parent":"main","new":"path","id":"_13332","d":"M149.25,1 L149.25,5","style":{"stroke":"rgb(0,0,255)","fill":"none"},"transform":"matrix(1,0,0,1,8623,81)"},{"parent":"main","new":"text","id":"_13333","x":0,"y":0,"child":"","style":{"fill":"rgb(0,0,0)","font-family":"Bravura","font-size":22},"transform":"matrix(1,0,0,1,9006,75)"},{"parent":"main","new":"text","id":"_13334","x":0,"y":0,"child":"","style":{"fill":"rgb(0,0,0)","font-family":"Bravura","font-size":24},"transform":"matrix(1,0,0,1,8998.5556640625,75)"},{"parent":"main","new":"path","id":"_13335","d":"M5,3 L149.25,3","style":{"stroke-width":2,"stroke":"rgb(0,0,255)","fill":"none"},"transform":"matrix(1,0,0,1,9008,72)"},{"parent":"main","new":"path","id":"_13336","d":"M149.25,1 L149.25,5","style":{"stroke":"rgb(0,0,255)","fill":"none"},"transform":"matrix(1,0,0,1,9008,72)"},{"parent":"main","new":"path","id":"_13337","d":"M9315.599609375,84 L9325.400390625,84","style":{"stroke-width":0.4},"transform":"matrix(1,0,0,1,0,0)"},{"parent":"main","new":"text","id":"_13338","x":0,"y":0,"child":"","style":{"fill":"rgb(0,0,0)","font-family":"Bravura","font-size":22},"transform":"matrix(1,0,0,1,9317,87)"},{"parent":"main","new":"path","id":"_13339","d":"M5,3 L149.25,3","style":{"stroke-width":2,"stroke":"rgb(0,0,255)","fill":"none"},"transform":"matrix(1,0,0,1,9319,84)"},{"parent":"main","new":"path","id":"_13340","d":"M149.25,1 L149.25,5","style":{"stroke":"rgb(0,0,255)","fill":"none"},"transform":"matrix(1,0,0,1,9319,84)"},{"parent":"main","new":"text","id":"_13341","x":0,"y":0,"child":"","style":{"fill":"rgb(0,0,0)","font-family":"Bravura","font-size":22},"transform":"matrix(1,0,0,1,9628,78)"},{"parent":"main","new":"path","id":"_13342","d":"M5,3 L149.25,3","style":{"stroke-width":2,"stroke":"rgb(0,0,255)","fill":"none"},"transform":"matrix(1,0,0,1,9630,75)"},{"parent":"main","new":"path","id":"_13343","d":"M149.25,1 L149.25,5","style":{"stroke":"rgb(0,0,255)","fill":"none"},"transform":"matrix(1,0,0,1,9630,75)"},{"parent":"main","new":"text","id":"_13344","x":0,"y":0,"child":"","style":{"fill":"rgb(0,0,0)","font-family":"Bravura","font-size":22},"transform":"matrix(1,0,0,1,10013,69)"},{"parent":"main","new":"path","id":"_13345","d":"M5,3 L149.25,3","style":{"stroke-width":2,"stroke":"rgb(0,0,255)","fill":"none"},"transform":"matrix(1,0,0,1,10015,66)"},{"parent":"main","new":"path","id":"_13346","d":"M149.25,1 L149.25,5","style":{"stroke":"rgb(0,0,255)","fill":"none"},"transform":"matrix(1,0,0,1,10015,66)"},{"parent":"main","new":"text","id":"_13347","x":0,"y":0,"child":"","style":{"fill":"rgb(0,0,0)","font-family":"Bravura","font-size":22},"transform":"matrix(1,0,0,1,10272,81)"},{"parent":"main","new":"text","id":"_13348","x":0,"y":0,"child":"","style":{"fill":"rgb(0,0,0)","font-family":"Bravura","font-size":24},"transform":"matrix(1,0,0,1,10267.5556640625,81)"},{"parent":"main","new":"path","id":"_13349","d":"M5,3 L149.25,3","style":{"stroke-width":2,"stroke":"rgb(0,0,255)","fill":"none"},"transform":"matrix(1,0,0,1,10274,78)"},{"parent":"main","new":"path","id":"_13350","d":"M149.25,1 L149.25,5","style":{"stroke":"rgb(0,0,255)","fill":"none"},"transform":"matrix(1,0,0,1,10274,78)"},{"parent":"main","new":"path","id":"_17232","d":"M0,0L100,7.5,0,15","style":{"fill":"none","stroke-width":0.6},"transform":"matrix(21.81,0,0,1,8091,108)"},{"parent":"main","new":"text","id":"_17233","x":0,"y":0,"child":"","style":{"fill":"rgb(0,0,0)","font-family":"Bravura","font-size":22},"transform":"matrix(1,0,0,1,10585,72)"},{"parent":"main","new":"text","id":"_17234","x":0,"y":0,"child":"","style":{"fill":"rgb(0,0,0)","font-family":"Bravura","font-size":24},"transform":"matrix(1,0,0,1,10577.5556640625,72)"},{"parent":"main","new":"text","id":"_17235","x":0,"y":0,"child":"","style":{"fill":"rgb(0,0,0)","font-family":"Bravura","font-size":24},"transform":"matrix(1,0,0,1,10582,96)"},{"parent":"main","new":"path","id":"_17236","d":"M5,3 L171.571433,3","style":{"stroke-width":2,"stroke":"rgb(0,0,255)","fill":"none"},"transform":"matrix(1,0,0,1,10587,69)"},{"parent":"main","new":"path","id":"_17237","d":"M171.571433,1 L171.571433,5","style":{"stroke":"rgb(0,0,255)","fill":"none"},"transform":"matrix(1,0,0,1,10587,69)"},{"parent":"main","new":"path","id":"_17238","d":"M10887.599609375,84 L10897.400390625,84","style":{"stroke-width":0.4},"transform":"matrix(1,0,0,1,0,0)"},{"parent":"main","new":"text","id":"_17239","x":0,"y":0,"child":"","style":{"fill":"rgb(0,0,0)","font-family":"Bravura","font-size":22},"transform":"matrix(1,0,0,1,10889,84)"},{"parent":"main","new":"text","id":"_17240","x":0,"y":0,"child":"","style":{"fill":"rgb(0,0,0)","font-family":"Bravura","font-size":24},"transform":"matrix(1,0,0,1,10881.5556640625,84)"},{"parent":"main","new":"path","id":"_17241","d":"M5,3 L171.571433,3","style":{"stroke-width":2,"stroke":"rgb(0,0,255)","fill":"none"},"transform":"matrix(1,0,0,1,10891,81)"},{"parent":"main","new":"path","id":"_17242","d":"M171.571433,1 L171.571433,5","style":{"stroke":"rgb(0,0,255)","fill":"none"},"transform":"matrix(1,0,0,1,10891,81)"},{"parent":"main","new":"text","id":"_17243","x":0,"y":0,"child":"","style":{"fill":"rgb(0,0,0)","font-family":"Bravura","font-size":22},"transform":"matrix(1,0,0,1,11198,75)"},{"parent":"main","new":"text","id":"_17244","x":0,"y":0,"child":"","style":{"fill":"rgb(0,0,0)","font-family":"Bravura","font-size":24},"transform":"matrix(1,0,0,1,11190.5556640625,75)"},{"parent":"main","new":"path","id":"_17245","d":"M5,3 L171.571433,3","style":{"stroke-width":2,"stroke":"rgb(0,0,255)","fill":"none"},"transform":"matrix(1,0,0,1,11200,72)"},{"parent":"main","new":"path","id":"_17246","d":"M171.571433,1 L171.571433,5","style":{"stroke":"rgb(0,0,255)","fill":"none"},"transform":"matrix(1,0,0,1,11200,72)"},{"parent":"main","new":"path","id":"_17247","d":"M11617.599609375,84 L11627.400390625,84","style":{"stroke-width":0.4},"transform":"matrix(1,0,0,1,0,0)"},{"parent":"main","new":"text","id":"_17248","x":0,"y":0,"child":"","style":{"fill":"rgb(0,0,0)","font-family":"Bravura","font-size":22},"transform":"matrix(1,0,0,1,11619,87)"},{"parent":"main","new":"path","id":"_17249","d":"M5,3 L171.571433,3","style":{"stroke-width":2,"stroke":"rgb(0,0,255)","fill":"none"},"transform":"matrix(1,0,0,1,11621,84)"},{"parent":"main","new":"path","id":"_17250","d":"M171.571433,1 L171.571433,5","style":{"stroke":"rgb(0,0,255)","fill":"none"},"transform":"matrix(1,0,0,1,11621,84)"},{"parent":"main","new":"text","id":"_17251","x":0,"y":0,"child":"","style":{"fill":"rgb(0,0,0)","font-family":"Bravura","font-size":22},"transform":"matrix(1,0,0,1,12015,78)"},{"parent":"main","new":"path","id":"_17252","d":"M5,3 L171.571433,3","style":{"stroke-width":2,"stroke":"rgb(0,0,255)","fill":"none"},"transform":"matrix(1,0,0,1,12017,75)"},{"parent":"main","new":"path","id":"_17253","d":"M171.571433,1 L171.571433,5","style":{"stroke":"rgb(0,0,255)","fill":"none"},"transform":"matrix(1,0,0,1,12017,75)"},{"parent":"main","new":"text","id":"_17254","x":0,"y":0,"child":"","style":{"fill":"rgb(0,0,0)","font-family":"Bravura","font-size":22},"transform":"matrix(1,0,0,1,12438,69)"},{"parent":"main","new":"path","id":"_17255","d":"M5,3 L171.571433,3","style":{"stroke-width":2,"stroke":"rgb(0,0,255)","fill":"none"},"transform":"matrix(1,0,0,1,12440,66)"},{"parent":"main","new":"path","id":"_17256","d":"M171.571433,1 L171.571433,5","style":{"stroke":"rgb(0,0,255)","fill":"none"},"transform":"matrix(1,0,0,1,12440,66)"},{"parent":"main","new":"text","id":"_17257","x":0,"y":0,"child":"","style":{"fill":"rgb(0,0,0)","font-family":"Bravura","font-size":22},"transform":"matrix(1,0,0,1,12740,81)"},{"parent":"main","new":"path","id":"_17258","d":"M5,3 L171.571433,3","style":{"stroke-width":2,"stroke":"rgb(0,0,255)","fill":"none"},"transform":"matrix(1,0,0,1,12742,78)"},{"parent":"main","new":"path","id":"_17259","d":"M171.571433,1 L171.571433,5","style":{"stroke":"rgb(0,0,255)","fill":"none"},"transform":"matrix(1,0,0,1,12742,78)"},{"parent":"main","new":"path","id":"_21133","d":"M0,0L100,7.5,0,15","style":{"fill":"none","stroke-width":0.6},"transform":"matrix(21.49,0,0,1,10591,108)"},{"parent":"main","new":"path","id":"_21134","d":"M13083.599609375,84 L13093.400390625,84","style":{"stroke-width":0.4},"transform":"matrix(1,0,0,1,0,0)"},{"parent":"main","new":"text","id":"_21135","x":0,"y":0,"child":"","style":{"fill":"rgb(0,0,0)","font-family":"Bravura","font-size":22},"transform":"matrix(1,0,0,1,13085,84)"},{"parent":"main","new":"text","id":"_21136","x":0,"y":0,"child":"","style":{"fill":"rgb(0,0,0)","font-family":"Bravura","font-size":24},"transform":"matrix(1,0,0,1,13077.5556640625,84)"},{"parent":"main","new":"text","id":"_21137","x":0,"y":0,"child":"","style":{"fill":"rgb(0,0,0)","font-family":"Bravura","font-size":24},"transform":"matrix(1,0,0,1,13082,99)"},{"parent":"main","new":"path","id":"_21138","d":"M5,3 L201.333328,3","style":{"stroke-width":2,"stroke":"rgb(0,0,255)","fill":"none"},"transform":"matrix(1,0,0,1,13087,81)"},{"parent":"main","new":"path","id":"_21139","d":"M201.333328,1 L201.333328,5","style":{"stroke":"rgb(0,0,255)","fill":"none"},"transform":"matrix(1,0,0,1,13087,81)"},{"parent":"main","new":"text","id":"_21140","x":0,"y":0,"child":"","style":{"fill":"rgb(0,0,0)","font-family":"Bravura","font-size":22},"transform":"matrix(1,0,0,1,13441,75)"},{"parent":"main","new":"text","id":"_21141","x":0,"y":0,"child":"","style":{"fill":"rgb(0,0,0)","font-family":"Bravura","font-size":24},"transform":"matrix(1,0,0,1,13433.5556640625,75)"},{"parent":"main","new":"path","id":"_21142","d":"M5,3 L201.333328,3","style":{"stroke-width":2,"stroke":"rgb(0,0,255)","fill":"none"},"transform":"matrix(1,0,0,1,13443,72)"},{"parent":"main","new":"path","id":"_21143","d":"M201.333328,1 L201.333328,5","style":{"stroke":"rgb(0,0,255)","fill":"none"},"transform":"matrix(1,0,0,1,13443,72)"},{"parent":"main","new":"path","id":"_21144","d":"M13854.599609375,84 L13864.400390625,84","style":{"stroke-width":0.4},"transform":"matrix(1,0,0,1,0,0)"},{"parent":"main","new":"text","id":"_21145","x":0,"y":0,"child":"","style":{"fill":"rgb(0,0,0)","font-family":"Bravura","font-size":22},"transform":"matrix(1,0,0,1,13856,87)"},{"parent":"main","new":"path","id":"_21146","d":"M5,3 L201.333328,3","style":{"stroke-width":2,"stroke":"rgb(0,0,255)","fill":"none"},"transform":"matrix(1,0,0,1,13858,84)"},{"parent":"main","new":"path","id":"_21147","d":"M201.333328,1 L201.333328,5","style":{"stroke":"rgb(0,0,255)","fill":"none"},"transform":"matrix(1,0,0,1,13858,84)"},{"parent":"main","new":"text","id":"_21148","x":0,"y":0,"child":"","style":{"fill":"rgb(0,0,0)","font-family":"Bravura","font-size":22},"transform":"matrix(1,0,0,1,14317,78)"},{"parent":"main","new":"path","id":"_21149","d":"M5,3 L201.333328,3","style":{"stroke-width":2,"stroke":"rgb(0,0,255)","fill":"none"},"transform":"matrix(1,0,0,1,14319,75)"},{"parent":"main","new":"path","id":"_21150","d":"M201.333328,1 L201.333328,5","style":{"stroke":"rgb(0,0,255)","fill":"none"},"transform":"matrix(1,0,0,1,14319,75)"},{"parent":"main","new":"text","id":"_21151","x":0,"y":0,"child":"","style":{"fill":"rgb(0,0,0)","font-family":"Bravura","font-size":22},"transform":"matrix(1,0,0,1,14778,69)"},{"parent":"main","new":"path","id":"_21152","d":"M5,3 L201.333328,3","style":{"stroke-width":2,"stroke":"rgb(0,0,255)","fill":"none"},"transform":"matrix(1,0,0,1,14780,66)"},{"parent":"main","new":"path","id":"_21153","d":"M201.333328,1 L201.333328,5","style":{"stroke":"rgb(0,0,255)","fill":"none"},"transform":"matrix(1,0,0,1,14780,66)"},{"parent":"main","new":"text","id":"_21154","x":0,"y":0,"child":"","style":{"fill":"rgb(0,0,0)","font-family":"Bravura","font-size":22},"transform":"matrix(1,0,0,1,15188,81)"},{"parent":"main","new":"path","id":"_21155","d":"M5,3 L201.333328,3","style":{"stroke-width":2,"stroke":"rgb(0,0,255)","fill":"none"},"transform":"matrix(1,0,0,1,15190,78)"},{"parent":"main","new":"path","id":"_21156","d":"M201.333328,1 L201.333328,5","style":{"stroke":"rgb(0,0,255)","fill":"none"},"transform":"matrix(1,0,0,1,15190,78)"},{"parent":"main","new":"path","id":"_24986","d":"M0,0L100,7.5,0,15","style":{"fill":"none","stroke-width":0.6},"transform":"matrix(20.97,0,0,1,13091,108)"},{"parent":"main","new":"text","id":"_24987","x":0,"y":0,"child":"","style":{"fill":"rgb(0,0,0)","font-family":"Bravura","font-size":22},"transform":"matrix(1,0,0,1,15585,75)"},{"parent":"main","new":"text","id":"_24988","x":0,"y":0,"child":"","style":{"fill":"rgb(0,0,0)","font-family":"Bravura","font-size":24},"transform":"matrix(1,0,0,1,15577.5556640625,75)"},{"parent":"main","new":"text","id":"_24989","x":0,"y":0,"child":"","style":{"fill":"rgb(0,0,0)","font-family":"Bravura","font-size":24},"transform":"matrix(1,0,0,1,15582,96)"},{"parent":"main","new":"path","id":"_24990","d":"M5,3 L201.333328,3","style":{"stroke-width":2,"stroke":"rgb(0,0,255)","fill":"none"},"transform":"matrix(1,0,0,1,15587,72)"},{"parent":"main","new":"path","id":"_24991","d":"M201.333328,1 L201.333328,5","style":{"stroke":"rgb(0,0,255)","fill":"none"},"transform":"matrix(1,0,0,1,15587,72)"},{"parent":"main","new":"path","id":"_24992","d":"M16011.599609375,84 L16021.400390625,84","style":{"stroke-width":0.4},"transform":"matrix(1,0,0,1,0,0)"},{"parent":"main","new":"text","id":"_24993","x":0,"y":0,"child":"","style":{"fill":"rgb(0,0,0)","font-family":"Bravura","font-size":22},"transform":"matrix(1,0,0,1,16013,87)"},{"parent":"main","new":"path","id":"_24994","d":"M5,3 L201.333328,3","style":{"stroke-width":2,"stroke":"rgb(0,0,255)","fill":"none"},"transform":"matrix(1,0,0,1,16015,84)"},{"parent":"main","new":"path","id":"_24995","d":"M201.333328,1 L201.333328,5","style":{"stroke":"rgb(0,0,255)","fill":"none"},"transform":"matrix(1,0,0,1,16015,84)"},{"parent":"main","new":"text","id":"_24996","x":0,"y":0,"child":"","style":{"fill":"rgb(0,0,0)","font-family":"Bravura","font-size":22},"transform":"matrix(1,0,0,1,16557,78)"},{"parent":"main","new":"path","id":"_24997","d":"M5,3 L201.333328,3","style":{"stroke-width":2,"stroke":"rgb(0,0,255)","fill":"none"},"transform":"matrix(1,0,0,1,16559,75)"},{"parent":"main","new":"path","id":"_24998","d":"M201.333328,1 L201.333328,5","style":{"stroke":"rgb(0,0,255)","fill":"none"},"transform":"matrix(1,0,0,1,16559,75)"},{"parent":"main","new":"text","id":"_24999","x":0,"y":0,"child":"","style":{"fill":"rgb(0,0,0)","font-family":"Bravura","font-size":22},"transform":"matrix(1,0,0,1,17077,69)"},{"parent":"main","new":"path","id":"_25000","d":"M5,3 L201.333328,3","style":{"stroke-width":2,"stroke":"rgb(0,0,255)","fill":"none"},"transform":"matrix(1,0,0,1,17079,66)"},{"parent":"main","new":"path","id":"_25001","d":"M201.333328,1 L201.333328,5","style":{"stroke":"rgb(0,0,255)","fill":"none"},"transform":"matrix(1,0,0,1,17079,66)"},{"parent":"main","new":"text","id":"_25002","x":0,"y":0,"child":"","style":{"fill":"rgb(0,0,0)","font-family":"Bravura","font-size":22},"transform":"matrix(1,0,0,1,17618,81)"},{"parent":"main","new":"path","id":"_25003","d":"M5,3 L201.333328,3","style":{"stroke-width":2,"stroke":"rgb(0,0,255)","fill":"none"},"transform":"matrix(1,0,0,1,17620,78)"},{"parent":"main","new":"path","id":"_25004","d":"M201.333328,1 L201.333328,5","style":{"stroke":"rgb(0,0,255)","fill":"none"},"transform":"matrix(1,0,0,1,17620,78)"},{"parent":"main","new":"path","id":"_28833","d":"M0,0L100,7.5,0,15","style":{"fill":"none","stroke-width":0.6},"transform":"matrix(20.27,0,0,1,15591,108)"},{"parent":"main","new":"path","id":"_28834","d":"M18083.599609375,84 L18093.400390625,84","style":{"stroke-width":0.4},"transform":"matrix(1,0,0,1,0,0)"},{"parent":"main","new":"text","id":"_28835","x":0,"y":0,"child":"","style":{"fill":"rgb(0,0,0)","font-family":"Bravura","font-size":22},"transform":"matrix(1,0,0,1,18085,87)"},{"parent":"main","new":"text","id":"_28836","x":0,"y":0,"child":"","style":{"fill":"rgb(0,0,0)","font-family":"Bravura","font-size":24},"transform":"matrix(1,0,0,1,18082,102)"},{"parent":"main","new":"path","id":"_28837","d":"M5,3 L201.333328,3","style":{"stroke-width":2,"stroke":"rgb(0,0,255)","fill":"none"},"transform":"matrix(1,0,0,1,18087,84)"},{"parent":"main","new":"path","id":"_28838","d":"M201.333328,1 L201.333328,5","style":{"stroke":"rgb(0,0,255)","fill":"none"},"transform":"matrix(1,0,0,1,18087,84)"},{"parent":"main","new":"text","id":"_28839","x":0,"y":0,"child":"","style":{"fill":"rgb(0,0,0)","font-family":"Bravura","font-size":22},"transform":"matrix(1,0,0,1,18621,78)"},{"parent":"main","new":"path","id":"_28840","d":"M5,3 L201.333328,3","style":{"stroke-width":2,"stroke":"rgb(0,0,255)","fill":"none"},"transform":"matrix(1,0,0,1,18623,75)"},{"parent":"main","new":"path","id":"_28841","d":"M201.333328,1 L201.333328,5","style":{"stroke":"rgb(0,0,255)","fill":"none"},"transform":"matrix(1,0,0,1,18623,75)"},{"parent":"main","new":"text","id":"_28842","x":0,"y":0,"child":"","style":{"fill":"rgb(0,0,0)","font-family":"Bravura","font-size":22},"transform":"matrix(1,0,0,1,19317,69)"},{"parent":"main","new":"path","id":"_28843","d":"M5,3 L201.333328,3","style":{"stroke-width":2,"stroke":"rgb(0,0,255)","fill":"none"},"transform":"matrix(1,0,0,1,19319,66)"},{"parent":"main","new":"path","id":"_28844","d":"M201.333328,1 L201.333328,5","style":{"stroke":"rgb(0,0,255)","fill":"none"},"transform":"matrix(1,0,0,1,19319,66)"},{"parent":"main","new":"text","id":"_28845","x":0,"y":0,"child":"","style":{"fill":"rgb(0,0,0)","font-family":"Bravura","font-size":22},"transform":"matrix(1,0,0,1,20013,81)"},{"parent":"main","new":"path","id":"_28846","d":"M5,3 L201.333328,3","style":{"stroke-width":2,"stroke":"rgb(0,0,255)","fill":"none"},"transform":"matrix(1,0,0,1,20015,78)"},{"parent":"main","new":"path","id":"_28847","d":"M201.333328,1 L201.333328,5","style":{"stroke":"rgb(0,0,255)","fill":"none"},"transform":"matrix(1,0,0,1,20015,78)"},{"parent":"main","new":"path","id":"_32689","d":"M0,0L100,7.5,0,15","style":{"fill":"none","stroke-width":0.6},"transform":"matrix(19.22,0,0,1,18091,108)"},{"parent":"main","new":"text","id":"_32690","x":0,"y":0,"child":"","style":{"fill":"rgb(0,0,0)","font-family":"Bravura","font-size":22},"transform":"matrix(1,0,0,1,20585,78)"},{"parent":"main","new":"text","id":"_32691","x":0,"y":0,"child":"","style":{"fill":"rgb(0,0,0)","font-family":"Bravura","font-size":24},"transform":"matrix(1,0,0,1,20582,96)"},{"parent":"main","new":"path","id":"_32692","d":"M5,3 L201.333328,3","style":{"stroke-width":2,"stroke":"rgb(0,0,255)","fill":"none"},"transform":"matrix(1,0,0,1,20587,75)"},{"parent":"main","new":"path","id":"_32693","d":"M201.333328,1 L201.333328,5","style":{"stroke":"rgb(0,0,255)","fill":"none"},"transform":"matrix(1,0,0,1,20587,75)"},{"parent":"main","new":"text","id":"_32694","x":0,"y":0,"child":"","style":{"fill":"rgb(0,0,0)","font-family":"Bravura","font-size":22},"transform":"matrix(1,0,0,1,21356,69)"},{"parent":"main","new":"path","id":"_32695","d":"M5,3 L201.333328,3","style":{"stroke-width":2,"stroke":"rgb(0,0,255)","fill":"none"},"transform":"matrix(1,0,0,1,21358,66)"},{"parent":"main","new":"path","id":"_32696","d":"M201.333328,1 L201.333328,5","style":{"stroke":"rgb(0,0,255)","fill":"none"},"transform":"matrix(1,0,0,1,21358,66)"},{"parent":"main","new":"text","id":"_32697","x":0,"y":0,"child":"","style":{"fill":"rgb(0,0,0)","font-family":"Bravura","font-size":22},"transform":"matrix(1,0,0,1,22278,81)"},{"parent":"main","new":"path","id":"_32698","d":"M5,3 L201.333328,3","style":{"stroke-width":2,"stroke":"rgb(0,0,255)","fill":"none"},"transform":"matrix(1,0,0,1,22280,78)"},{"parent":"main","new":"path","id":"_32699","d":"M201.333328,1 L201.333328,5","style":{"stroke":"rgb(0,0,255)","fill":"none"},"transform":"matrix(1,0,0,1,22280,78)"},{"parent":"main","new":"path","id":"_36581","d":"M0,0L100,7.5,0,15","style":{"fill":"none","stroke-width":0.6},"transform":"matrix(16.87,0,0,1,20591,108)"},{"parent":"main","new":"text","id":"_36582","x":0,"y":0,"child":"","style":{"fill":"rgb(0,0,0)","font-family":"Bravura","font-size":22},"transform":"matrix(1,0,0,1,23085,69)"},{"parent":"main","new":"text","id":"_36583","x":0,"y":0,"child":"","style":{"fill":"rgb(0,0,0)","font-family":"Bravura","font-size":24},"transform":"matrix(1,0,0,1,23082,96)"},{"parent":"main","new":"path","id":"_36584","d":"M5,3 L201.333328,3","style":{"stroke-width":2,"stroke":"rgb(0,0,255)","fill":"none"},"transform":"matrix(1,0,0,1,23087,66)"},{"parent":"main","new":"path","id":"_36585","d":"M201.333328,1 L201.333328,5","style":{"stroke":"rgb(0,0,255)","fill":"none"},"transform":"matrix(1,0,0,1,23087,66)"},{"parent":"main","new":"text","id":"_36586","x":0,"y":0,"child":"","style":{"fill":"rgb(0,0,0)","font-family":"Bravura","font-size":22},"transform":"matrix(1,0,0,1,24317,81)"},{"parent":"main","new":"path","id":"_36587","d":"M5,3 L201.333328,3","style":{"stroke-width":2,"stroke":"rgb(0,0,255)","fill":"none"},"transform":"matrix(1,0,0,1,24319,78)"},{"parent":"main","new":"path","id":"_36588","d":"M201.333328,1 L201.333328,5","style":{"stroke":"rgb(0,0,255)","fill":"none"},"transform":"matrix(1,0,0,1,24319,78)"},{"parent":"main","new":"path","id":"_40463","d":"M0,0L100,7.5,0,15","style":{"fill":"none","stroke-width":0.6},"transform":"matrix(12.26,0,0,1,23091,108)"},{"parent":"main","new":"text","id":"_40464","x":0,"y":0,"child":"","style":{"fill":"rgb(0,0,0)","font-family":"Bravura","font-size":22},"transform":"matrix(1,0,0,1,25585,81)"},{"parent":"main","new":"text","id":"_40465","x":0,"y":0,"child":"","style":{"fill":"rgb(0,0,0)","font-family":"Bravura","font-size":24},"transform":"matrix(1,0,0,1,25582,96)"},{"parent":"main","new":"path","id":"_40466","d":"M5,3 L201.333328,3","style":{"stroke-width":2,"stroke":"rgb(0,0,255)","fill":"none"},"transform":"matrix(1,0,0,1,25587,78)"},{"parent":"main","new":"path","id":"_44381","d":"M201.333328,1 L201.333328,5","style":{"stroke":"rgb(0,0,255)","fill":"none"},"transform":"matrix(1,0,0,1,25587,78)"},{"parent":"main","new":"text","id":"_44382","x":0,"y":0,"child":"","style":{"fill":"rgb(0,0,0)","font-family":"Bravura","font-size":22},"transform":"matrix(1,0,0,1,28085,72)"},{"parent":"main","new":"text","id":"_44383","x":0,"y":0,"child":"","style":{"fill":"rgb(0,0,0)","font-family":"Bravura","font-size":24},"transform":"matrix(1,0,0,1,28082,96)"},{"parent":"main","new":"path","id":"_44384","d":"M5,3 L97.166664,3","style":{"stroke-width":2,"stroke":"rgb(0,0,255)","fill":"none"},"transform":"matrix(1,0,0,1,28087,69)"},{"parent":"main","new":"path","id":"_44385","d":"M97.166664,1 L97.166664,5","style":{"stroke":"rgb(0,0,255)","fill":"none"},"transform":"matrix(1,0,0,1,28087,69)"},{"parent":"main","new":"path","id":"_44386","d":"M28265.599609375,84 L28275.400390625,84","style":{"stroke-width":0.4},"transform":"matrix(1,0,0,1,0,0)"},{"parent":"main","new":"text","id":"_44387","x":0,"y":0,"child":"","style":{"fill":"rgb(0,0,0)","font-family":"Bravura","font-size":22},"transform":"matrix(1,0,0,1,28267,84)"},{"parent":"main","new":"path","id":"_44388","d":"M5,3 L97.166664,3","style":{"stroke-width":2,"stroke":"rgb(0,0,255)","fill":"none"},"transform":"matrix(1,0,0,1,28269,81)"},{"parent":"main","new":"path","id":"_44389","d":"M97.166664,1 L97.166664,5","style":{"stroke":"rgb(0,0,255)","fill":"none"},"transform":"matrix(1,0,0,1,28269,81)"},{"parent":"main","new":"text","id":"_44390","x":0,"y":0,"child":"","style":{"fill":"rgb(0,0,0)","font-family":"Bravura","font-size":22},"transform":"matrix(1,0,0,1,28441,75)"},{"parent":"main","new":"path","id":"_44391","d":"M5,3 L97.166664,3","style":{"stroke-width":2,"stroke":"rgb(0,0,255)","fill":"none"},"transform":"matrix(1,0,0,1,28443,72)"},{"parent":"main","new":"path","id":"_44392","d":"M97.166664,1 L97.166664,5","style":{"stroke":"rgb(0,0,255)","fill":"none"},"transform":"matrix(1,0,0,1,28443,72)"},{"parent":"main","new":"path","id":"_44393","d":"M28619.599609375,84 L28629.400390625,84","style":{"stroke-width":0.4},"transform":"matrix(1,0,0,1,0,0)"},{"parent":"main","new":"path","id":"_44394","d":"M28619.599609375,90 L28629.400390625,90","style":{"stroke-width":0.4},"transform":"matrix(1,0,0,1,0,0)"},{"parent":"main","new":"text","id":"_44395","x":0,"y":0,"child":"","style":{"fill":"rgb(0,0,0)","font-family":"Bravura","font-size":22},"transform":"matrix(1,0,0,1,28621,90)"},{"parent":"main","new":"text","id":"_44396","x":0,"y":0,"child":"","style":{"fill":"rgb(0,0,0)","font-family":"Bravura","font-size":24},"transform":"matrix(1,0,0,1,28613.5546875,90)"},{"parent":"main","new":"path","id":"_44397","d":"M5,3 L97.166664,3","style":{"stroke-width":2,"stroke":"rgb(0,0,255)","fill":"none"},"transform":"matrix(1,0,0,1,28623,87)"},{"parent":"main","new":"path","id":"_44398","d":"M97.166664,1 L97.166664,5","style":{"stroke":"rgb(0,0,255)","fill":"none"},"transform":"matrix(1,0,0,1,28623,87)"},{"parent":"main","new":"text","id":"_44399","x":0,"y":0,"child":"","style":{"fill":"rgb(0,0,0)","font-family":"Bravura","font-size":22},"transform":"matrix(1,0,0,1,28856,81)"},{"parent":"main","new":"text","id":"_44400","x":0,"y":0,"child":"","style":{"fill":"rgb(0,0,0)","font-family":"Bravura","font-size":24},"transform":"matrix(1,0,0,1,28848.5546875,81)"},{"parent":"main","new":"path","id":"_44401","d":"M5,3 L97.166664,3","style":{"stroke-width":2,"stroke":"rgb(0,0,255)","fill":"none"},"transform":"matrix(1,0,0,1,28858,78)"},{"parent":"main","new":"path","id":"_44402","d":"M97.166664,1 L97.166664,5","style":{"stroke":"rgb(0,0,255)","fill":"none"},"transform":"matrix(1,0,0,1,28858,78)"},{"parent":"main","new":"text","id":"_44403","x":0,"y":0,"child":"","style":{"fill":"rgb(0,0,0)","font-family":"Bravura","font-size":22},"transform":"matrix(1,0,0,1,29093,72)"},{"parent":"main","new":"text","id":"_44404","x":0,"y":0,"child":"","style":{"fill":"rgb(0,0,0)","font-family":"Bravura","font-size":24},"transform":"matrix(1,0,0,1,29085.5546875,72)"},{"parent":"main","new":"path","id":"_44405","d":"M5,3 L97.166664,3","style":{"stroke-width":2,"stroke":"rgb(0,0,255)","fill":"none"},"transform":"matrix(1,0,0,1,29095,69)"},{"parent":"main","new":"path","id":"_44406","d":"M97.166664,1 L97.166664,5","style":{"stroke":"rgb(0,0,255)","fill":"none"},"transform":"matrix(1,0,0,1,29095,69)"},{"parent":"main","new":"path","id":"_44407","d":"M29315.599609375,84 L29325.400390625,84","style":{"stroke-width":0.4},"transform":"matrix(1,0,0,1,0,0)"},{"parent":"main","new":"text","id":"_44408","x":0,"y":0,"child":"","style":{"fill":"rgb(0,0,0)","font-family":"Bravura","font-size":22},"transform":"matrix(1,0,0,1,29317,84)"},{"parent":"main","new":"text","id":"_44409","x":0,"y":0,"child":"","style":{"fill":"rgb(0,0,0)","font-family":"Bravura","font-size":24},"transform":"matrix(1,0,0,1,29309.5546875,84)"},{"parent":"main","new":"path","id":"_44410","d":"M5,3 L97.166664,3","style":{"stroke-width":2,"stroke":"rgb(0,0,255)","fill":"none"},"transform":"matrix(1,0,0,1,29319,81)"},{"parent":"main","new":"path","id":"_44411","d":"M97.166664,1 L97.166664,5","style":{"stroke":"rgb(0,0,255)","fill":"none"},"transform":"matrix(1,0,0,1,29319,81)"},{"parent":"main","new":"text","id":"_44412","x":0,"y":0,"child":"","style":{"fill":"rgb(0,0,0)","font-family":"Bravura","font-size":22},"transform":"matrix(1,0,0,1,29541,75)"},{"parent":"main","new":"text","id":"_44413","x":0,"y":0,"child":"","style":{"fill":"rgb(0,0,0)","font-family":"Bravura","font-size":24},"transform":"matrix(1,0,0,1,29533.5546875,75)"},{"parent":"main","new":"path","id":"_44414","d":"M5,3 L97.166664,3","style":{"stroke-width":2,"stroke":"rgb(0,0,255)","fill":"none"},"transform":"matrix(1,0,0,1,29543,72)"},{"parent":"main","new":"path","id":"_44415","d":"M97.166664,1 L97.166664,5","style":{"stroke":"rgb(0,0,255)","fill":"none"},"transform":"matrix(1,0,0,1,29543,72)"},{"parent":"main","new":"path","id":"_44416","d":"M29776.599609375,84 L29786.400390625,84","style":{"stroke-width":0.4},"transform":"matrix(1,0,0,1,0,0)"},{"parent":"main","new":"text","id":"_44417","x":0,"y":0,"child":"","style":{"fill":"rgb(0,0,0)","font-family":"Bravura","font-size":22},"transform":"matrix(1,0,0,1,29778,87)"},{"parent":"main","new":"path","id":"_44418","d":"M5,3 L97.166664,3","style":{"stroke-width":2,"stroke":"rgb(0,0,255)","fill":"none"},"transform":"matrix(1,0,0,1,29780,84)"},{"parent":"main","new":"path","id":"_44419","d":"M97.166664,1 L97.166664,5","style":{"stroke":"rgb(0,0,255)","fill":"none"},"transform":"matrix(1,0,0,1,29780,84)"},{"parent":"main","new":"text","id":"_44420","x":0,"y":0,"child":"","style":{"fill":"rgb(0,0,0)","font-family":"Bravura","font-size":22},"transform":"matrix(1,0,0,1,30013,78)"},{"parent":"main","new":"path","id":"_44421","d":"M5,3 L97.166664,3","style":{"stroke-width":2,"stroke":"rgb(0,0,255)","fill":"none"},"transform":"matrix(1,0,0,1,30015,75)"},{"parent":"main","new":"path","id":"_44422","d":"M97.166664,1 L97.166664,5","style":{"stroke":"rgb(0,0,255)","fill":"none"},"transform":"matrix(1,0,0,1,30015,75)"},{"parent":"main","new":"text","id":"_44423","x":0,"y":0,"child":"","style":{"fill":"rgb(0,0,0)","font-family":"Bravura","font-size":22},"transform":"matrix(1,0,0,1,30188,69)"},{"parent":"main","new":"path","id":"_44424","d":"M5,3 L97.166664,3","style":{"stroke-width":2,"stroke":"rgb(0,0,255)","fill":"none"},"transform":"matrix(1,0,0,1,30190,66)"},{"parent":"main","new":"path","id":"_44425","d":"M97.166664,1 L97.166664,5","style":{"stroke":"rgb(0,0,255)","fill":"none"},"transform":"matrix(1,0,0,1,30190,66)"},{"parent":"main","new":"text","id":"_44426","x":0,"y":0,"child":"","style":{"fill":"rgb(0,0,0)","font-family":"Bravura","font-size":22},"transform":"matrix(1,0,0,1,30354,81)"},{"parent":"main","new":"text","id":"_44427","x":0,"y":0,"child":"","style":{"fill":"rgb(0,0,0)","font-family":"Bravura","font-size":24},"transform":"matrix(1,0,0,1,30349.5546875,81)"},{"parent":"main","new":"path","id":"_44428","d":"M5,3 L97.166664,3","style":{"stroke-width":2,"stroke":"rgb(0,0,255)","fill":"none"},"transform":"matrix(1,0,0,1,30356,78)"},{"parent":"main","new":"path","id":"_44429","d":"M97.166664,1 L97.166664,5","style":{"stroke":"rgb(0,0,255)","fill":"none"},"transform":"matrix(1,0,0,1,30356,78)"},{"parent":"main","new":"path","id":"_47532","d":"M0,0L100,7.5,0,15","style":{"fill":"none","stroke-width":0.6},"transform":"matrix(22.63,0,0,1,28091,108)"},{"parent":"main","new":"path","id":"_47533","d":"M30583.599609375,84 L30593.400390625,84","style":{"stroke-width":0.4},"transform":"matrix(1,0,0,1,0,0)"},{"parent":"main","new":"text","id":"_47534","x":0,"y":0,"child":"","style":{"fill":"rgb(0,0,0)","font-family":"Bravura","font-size":22},"transform":"matrix(1,0,0,1,30585,84)"},{"parent":"main","new":"text","id":"_47535","x":0,"y":0,"child":"","style":{"fill":"rgb(0,0,0)","font-family":"Bravura","font-size":24},"transform":"matrix(1,0,0,1,30582,99)"},{"parent":"main","new":"path","id":"_47536","d":"M5,3 L43.000001,3","style":{"stroke-width":2,"stroke":"rgb(0,0,255)","fill":"none"},"transform":"matrix(1,0,0,1,30587,81)"},{"parent":"main","new":"path","id":"_48087","d":"M43.000001,1 L43.000001,5","style":{"stroke":"rgb(0,0,255)","fill":"none"},"transform":"matrix(1,0,0,1,30587,81)"},{"parent":"main","new":"path","id":"_48088","d":"M60,54 L33060,54,M60,60 L33060,60,M60,66 L33060,66,M60,72 L33060,72,M60,78 L33060,78,","style":{"stroke-width":0.4},"transform":"matrix(1,0,0,1,0,0)"}]},{"new":"g","id":"scoreGroup"},{"new":"g","id":"overlay"},{"parent":"overlay","new":"line","id":"playhead","x1":250,"x2":250,"y1":0,"y2":720,"style":{"stroke":"red","stroke-width":3,"stroke-opacity":0.5}},{"parent":"overlay","new":"line","id":"miniplayhead","x1":320,"x2":320,"y1":4,"y2":54,"style":{"stroke":"blue","stroke-width":3,"stroke-opacity":0.5}},{"parent":"overlay","new":"text","id":"timecount","x":195,"y":35},{"id":"score","parent":"scoreGroup","new":"use","href":"#defscore","x":250,"y":100},{"new":"g","id":"overlay_clef","transform":"matrix(1.5, 0, 0, 1.5, 0, 100)","child":{"id":"clef","parent":"overlay","new":"text","x":60,"y":72,"child":"","style":{"font-family":"Bravura","font-size":22},"transform":"matrix(1,0,0,1,0,0)"}},{"new":"g","id":"overlay_title","transform":"translate(320, 90)","child":{"id":"title","new":"text","x":0,"y":0,"child":": Dodekaederstern","style":{"font-family":"Times New Roman","font-size":30},"transform":"matrix(1,0,0,1,0,0)"}},{"id":"mini","parent":"scoreGroup","new":"use","href":"#defscore","y":18.48,"x":22628.571428571428,"transform":"scale(0.014141414141414142, 0.21645021645021645)","class":"noclick"},{"new":"text","id":"playerID","x":10,"y":90,"text":"39 flute"},{"parent":"overlay","id":"scrollbar","new":"rect","x":320,"y":4,"height":50,"width":700,"fill":"rgba(0,0,255,0.25)","onmousemove":"\n                    event.preventDefault();\n                    let x = event.clientX;\n                    if(event.buttons == 1){\n                        let r = ( ( x - 320 ) / 700) * 330;\n                        drawsocket.input({\n                            key: 'tween',\n                            val: [{\n                                id: 'score-anim',\n                                cmd: 'pause',\n                                time: r \n                            }, {\n                                id: 'miniscore-anim',\n                                cmd: 'pause',\n                                time: r\n                            }]\n                        });\n                        let uiTxt = document.getElementById('userinput');\n                        uiTxt.value = r;\n                        let button = document.getElementById('playbutton');\n                        if( button.classList.contains('ready') )\n                            button.classList.remove('ready');\n    \n                    }","ontouchmove":"\n                    event.preventDefault();\n                    let x = event.pageX;\n                    let r = ((x-320) / 700) * 330;\n                    drawsocket.input({\n                        key: 'tween',\n                        val: [{\n                            id: 'score-anim',\n                            cmd: 'pause',\n                            time: r \n                        }, {\n                            id: 'miniscore-anim',\n                            cmd: 'pause',\n                            time: r\n                        }]\n                    });\n                    let uiTxt = document.getElementById('userinput');\n                    uiTxt.value = r;\n                    "}]},{"key":"tween","val":[{"id":"score-anim","target":"#score","dur":330,"vars":{"x":-49500,"ease":"linear","paused":"true","onUpdate":{"function":" \n  if( this.time() % 1\t< 0.05){\n    let text = document.getElementById('timecount');\n    text.innerHTML = Math.floor( this.time() );\n  }\n"}}},{"id":"miniscore-anim","target":"#miniplayhead","dur":330,"vars":{"x":"+=700","ease":"linear","paused":"true"}}]}]}