{"/92":[{"key":"css","val":[{"selector":".ready","props":{"background-color":"lightblue","color":"black"}},{"selector":".noclick","props":{"user-select":"none","pointer-events":"none"}}]},{"key":"html","val":[{"parent":"forms","id":"UI","new":"div","style":{"position":"absolute","float":"left","width":"200px"}},{"parent":"UI","id":"playbutton","new":"button","text":"play","class":"button","style":{"float":"left"},"onclick":"if( !this.classList.contains('ready') )\n            {\n                this.classList.add('ready');\n                drawsocket.input({\n                    key: 'tween',\n                    val: [ {\n                        id: 'score-anim',\n                        cmd : 'play'\n                    }, {\n                        id: 'miniscore-anim',\n                        cmd : 'play'\n                    } ],\n                    timetag: Date.now()\n                });\n            } else {\n                this.classList.remove('ready');\n                let starttime = document.getElementById('userinput');\n                drawsocket.input({\n                    key: 'tween',\n                    val: [{\n                        id: 'score-anim',\n                        cmd: 'pause',\n                        time: starttime.value\n                    }, {\n                        id: 'miniscore-anim',\n                        cmd : 'pause',\n                        time: starttime.value\n                    }]\n                });\n            }"},{"parent":"UI","new":"label","for":"userinput","id":"sent","name":"sent","text":"start at time<br>","style":{"font-size":"60%","color":"gray","margin-left":"20px"}},{"parent":"UI","new":"input","type":"text","id":"userinput","name":"userinput","placeholder":"0","size":5,"onkeydown":"\n     if( drawsocket.submitOnEnterKey(this) ) { \n       let button = document.getElementById('playbutton');\n       if( button.classList.contains('ready') )\n            button.classList.remove('ready');\n\n       drawsocket.input({\n         key: 'tween',\n         val: [{\n           id: 'score-anim',\n           cmd: 'pause',\n           time: this.value\n         }, {\n          id: 'miniscore-anim',\n       \t\t cmd : 'pause',\n          time: this.value\n          }]\n       });\n     }","style":{"margin-left":"35px","text-align":"center"}}]},{"key":"svg","val":[{"new":"g","parent":"defs","id":"defscore","transform":"scale(1.5)","child":[{"parent":"main-svg","new":"g","id":"back"},{"parent":"main-svg","new":"g","id":"main"},{"parent":"main-svg","new":"g","id":"overlay"},{"parent":"main","new":"text","id":"_974","x":0,"y":0,"child":"8.8 Cello","style":{"fill":"rgb(0,0,0)","font-family":"Arial","font-size":10},"transform":"matrix(1,0,0,1,-70.361328125,59)"},{"parent":"main","new":"text","id":"_975","x":0,"y":0,"child":"","style":{"fill":"rgb(0,0,0)","font-family":"Bravura","font-size":22},"transform":"matrix(1,0,0,1,941,42)"},{"parent":"main","new":"text","id":"_976","x":0,"y":0,"child":"","style":{"fill":"rgb(0,0,0)","font-family":"Bravura","font-size":24},"transform":"matrix(1,0,0,1,938,87)"},{"parent":"main","new":"path","id":"_977","d":"M5,3 L468,3","style":{"stroke-width":2,"stroke":"rgb(0,0,255)","fill":"none"},"transform":"matrix(1,0,0,1,943,39)"},{"parent":"main","new":"path","id":"_1268","d":"M468,1 L468,5","style":{"stroke":"rgb(0,0,255)","fill":"none"},"transform":"matrix(1,0,0,1,943,39)"},{"parent":"main","new":"text","id":"_1424","x":1215,"y":810,"child":"Sempre%20Ah","style":{"stroke":"none","stroke-width":0,"font-family":"Arial","font-size":10},"transform":"matrix(1,0,0,1,0,0)"},{"parent":"main","new":"text","id":"_1580","x":1215,"y":1860,"child":"Sempre%20Ah","style":{"stroke":"none","stroke-width":0,"font-family":"Arial","font-size":10},"transform":"matrix(1,0,0,1,0,0)"},{"parent":"main","new":"text","id":"_1736","x":1215,"y":2910,"child":"Sempre%20Ah","style":{"stroke":"none","stroke-width":0,"font-family":"Arial","font-size":10},"transform":"matrix(1,0,0,1,0,0)"},{"parent":"main","new":"text","id":"_1892","x":1215,"y":3945,"child":"Sempre%20Ah","style":{"stroke":"none","stroke-width":0,"font-family":"Arial","font-size":10},"transform":"matrix(1,0,0,1,0,0)"},{"parent":"main","new":"text","id":"_2048","x":1215,"y":5010,"child":"Sempre%20Ah","style":{"stroke":"none","stroke-width":0,"font-family":"Arial","font-size":10},"transform":"matrix(1,0,0,1,0,0)"},{"parent":"main","new":"text","id":"_2204","x":1215,"y":6060,"child":"Sempre%20Ah","style":{"stroke":"none","stroke-width":0,"font-family":"Arial","font-size":10},"transform":"matrix(1,0,0,1,0,0)"},{"parent":"main","new":"text","id":"_2360","x":1215,"y":7110,"child":"Sempre%20Ah","style":{"stroke":"none","stroke-width":0,"font-family":"Arial","font-size":10},"transform":"matrix(1,0,0,1,0,0)"},{"parent":"main","new":"text","id":"_2516","x":1215,"y":8160,"child":"Sempre%20Ah","style":{"stroke":"none","stroke-width":0,"font-family":"Arial","font-size":10},"transform":"matrix(1,0,0,1,0,0)"},{"parent":"main","new":"text","id":"_2672","x":1215,"y":9210,"child":"Sempre%20Ah","style":{"stroke":"none","stroke-width":0,"font-family":"Arial","font-size":10},"transform":"matrix(1,0,0,1,0,0)"},{"parent":"main","new":"text","id":"_2828","x":1215,"y":10245,"child":"Sempre%20Ah","style":{"stroke":"none","stroke-width":0,"font-family":"Arial","font-size":10},"transform":"matrix(1,0,0,1,0,0)"},{"parent":"main","new":"text","id":"_2984","x":1215,"y":11310,"child":"Sempre%20Ah","style":{"stroke":"none","stroke-width":0,"font-family":"Arial","font-size":10},"transform":"matrix(1,0,0,1,0,0)"},{"parent":"main","new":"text","id":"_3998","x":1215,"y":12360,"child":"Sempre%20Ah","style":{"stroke":"none","stroke-width":0,"font-family":"Arial","font-size":10},"transform":"matrix(1,0,0,1,0,0)"},{"parent":"main","new":"text","id":"_3999","x":0,"y":0,"child":"","style":{"fill":"rgb(0,0,0)","font-family":"Bravura","font-size":22},"transform":"matrix(1,0,0,1,2541,42)"},{"parent":"main","new":"text","id":"_4000","x":0,"y":0,"child":"","style":{"fill":"rgb(0,0,0)","font-family":"Bravura","font-size":24},"transform":"matrix(1,0,0,1,2538,87)"},{"parent":"main","new":"path","id":"_4001","d":"M5,3 L368,3","style":{"stroke-width":2,"stroke":"rgb(0,0,255)","fill":"none"},"transform":"matrix(1,0,0,1,2543,39)"},{"parent":"main","new":"path","id":"_4541","d":"M368,1 L368,5","style":{"stroke":"rgb(0,0,255)","fill":"none"},"transform":"matrix(1,0,0,1,2543,39)"},{"parent":"main","new":"path","id":"_4542","d":"M2915.60009765625,39 L2925.39990234375,39","style":{"stroke-width":0.4},"transform":"matrix(1,0,0,1,0,0)"},{"parent":"main","new":"text","id":"_4543","x":0,"y":0,"child":"","style":{"fill":"rgb(0,0,0)","font-family":"Bravura","font-size":22},"transform":"matrix(1,0,0,1,2917,39)"},{"parent":"main","new":"text","id":"_4544","x":0,"y":0,"child":"","style":{"fill":"rgb(0,0,0)","font-family":"Bravura","font-size":24},"transform":"matrix(1,0,0,1,2911.5556640625,39)"},{"parent":"main","new":"text","id":"_4545","x":0,"y":0,"child":"","style":{"fill":"rgb(0,0,0)","font-family":"Bravura","font-size":24},"transform":"matrix(1,0,0,1,2914,87)"},{"parent":"main","new":"path","id":"_4546","d":"M5,3 L393,3","style":{"stroke-width":2,"stroke":"rgb(0,0,255)","fill":"none"},"transform":"matrix(1,0,0,1,2919,36)"},{"parent":"main","new":"path","id":"_6083","d":"M393,1 L393,5","style":{"stroke":"rgb(0,0,255)","fill":"none"},"transform":"matrix(1,0,0,1,2919,36)"},{"parent":"main","new":"path","id":"_6084","d":"M4115.60009765625,39 L4125.39990234375,39","style":{"stroke-width":0.4},"transform":"matrix(1,0,0,1,0,0)"},{"parent":"main","new":"text","id":"_6085","x":0,"y":0,"child":"","style":{"fill":"rgb(0,0,0)","font-family":"Bravura","font-size":22},"transform":"matrix(1,0,0,1,4117,39)"},{"parent":"main","new":"text","id":"_6086","x":0,"y":0,"child":"","style":{"fill":"rgb(0,0,0)","font-family":"Bravura","font-size":24},"transform":"matrix(1,0,0,1,4114,87)"},{"parent":"main","new":"path","id":"_6087","d":"M5,3 L26.333001,3","style":{"stroke-width":2,"stroke":"rgb(0,0,255)","fill":"none"},"transform":"matrix(1,0,0,1,4119,36)"},{"parent":"main","new":"path","id":"_6088","d":"M26.333001,1 L26.333001,5","style":{"stroke":"rgb(0,0,255)","fill":"none"},"transform":"matrix(1,0,0,1,4119,36)"},{"parent":"main","new":"text","id":"_6089","x":0,"y":0,"child":"","style":{"fill":"rgb(0,0,0)","font-family":"Bravura","font-size":22},"transform":"matrix(1,0,0,1,4149,45)"},{"parent":"main","new":"path","id":"_6090","d":"M5,3 L459.666002,3","style":{"stroke-width":2,"stroke":"rgb(0,0,255)","fill":"none"},"transform":"matrix(1,0,0,1,4151,42)"},{"parent":"main","new":"path","id":"_7660","d":"M459.666002,1 L459.666002,5","style":{"stroke":"rgb(0,0,255)","fill":"none"},"transform":"matrix(1,0,0,1,4151,42)"},{"parent":"main","new":"path","id":"_7661","d":"M5315.60009765625,39 L5325.39990234375,39","style":{"stroke-width":0.4},"transform":"matrix(1,0,0,1,0,0)"},{"parent":"main","new":"text","id":"_7662","x":0,"y":0,"child":"","style":{"fill":"rgb(0,0,0)","font-family":"Bravura","font-size":22},"transform":"matrix(1,0,0,1,5317,39)"},{"parent":"main","new":"text","id":"_7663","x":0,"y":0,"child":"","style":{"fill":"rgb(0,0,0)","font-family":"Bravura","font-size":24},"transform":"matrix(1,0,0,1,5309.5556640625,39)"},{"parent":"main","new":"text","id":"_7664","x":0,"y":0,"child":"","style":{"fill":"rgb(0,0,0)","font-family":"Bravura","font-size":24},"transform":"matrix(1,0,0,1,5314,87)"},{"parent":"main","new":"path","id":"_7665","d":"M5,3 L393,3","style":{"stroke-width":2,"stroke":"rgb(0,0,255)","fill":"none"},"transform":"matrix(1,0,0,1,5319,36)"},{"parent":"main","new":"path","id":"_8200","d":"M393,1 L393,5","style":{"stroke":"rgb(0,0,255)","fill":"none"},"transform":"matrix(1,0,0,1,5319,36)"},{"parent":"main","new":"text","id":"_8201","x":0,"y":0,"child":"","style":{"fill":"rgb(0,0,0)","font-family":"Bravura","font-size":22},"transform":"matrix(1,0,0,1,5744,48)"},{"parent":"main","new":"text","id":"_8202","x":0,"y":0,"child":"","style":{"fill":"rgb(0,0,0)","font-family":"Bravura","font-size":24},"transform":"matrix(1,0,0,1,5736.5556640625,48)"},{"parent":"main","new":"text","id":"_8203","x":0,"y":0,"child":"","style":{"fill":"rgb(0,0,0)","font-family":"Bravura","font-size":24},"transform":"matrix(1,0,0,1,5741,87)"},{"parent":"main","new":"path","id":"_8204","d":"M5,3 L468,3","style":{"stroke-width":2,"stroke":"rgb(0,0,255)","fill":"none"},"transform":"matrix(1,0,0,1,5746,45)"},{"parent":"main","new":"path","id":"_9204","d":"M468,1 L468,5","style":{"stroke":"rgb(0,0,255)","fill":"none"},"transform":"matrix(1,0,0,1,5746,45)"},{"parent":"main","new":"path","id":"_9205","d":"M6515.60009765625,39 L6525.39990234375,39","style":{"stroke-width":0.4},"transform":"matrix(1,0,0,1,0,0)"},{"parent":"main","new":"text","id":"_9206","x":0,"y":0,"child":"","style":{"fill":"rgb(0,0,0)","font-family":"Bravura","font-size":22},"transform":"matrix(1,0,0,1,6517,36)"},{"parent":"main","new":"text","id":"_9207","x":0,"y":0,"child":"","style":{"fill":"rgb(0,0,0)","font-family":"Bravura","font-size":24},"transform":"matrix(1,0,0,1,6514,87)"},{"parent":"main","new":"path","id":"_9208","d":"M5,3 L393,3","style":{"stroke-width":2,"stroke":"rgb(0,0,255)","fill":"none"},"transform":"matrix(1,0,0,1,6519,33)"},{"parent":"main","new":"path","id":"_10145","d":"M393,1 L393,5","style":{"stroke":"rgb(0,0,255)","fill":"none"},"transform":"matrix(1,0,0,1,6519,33)"},{"parent":"main","new":"text","id":"_10146","x":0,"y":0,"child":"","style":{"fill":"rgb(0,0,0)","font-family":"Bravura","font-size":22},"transform":"matrix(1,0,0,1,7341,48)"},{"parent":"main","new":"text","id":"_10147","x":0,"y":0,"child":"","style":{"fill":"rgb(0,0,0)","font-family":"Bravura","font-size":24},"transform":"matrix(1,0,0,1,7338,87)"},{"parent":"main","new":"path","id":"_10148","d":"M5,3 L368,3","style":{"stroke-width":2,"stroke":"rgb(0,0,255)","fill":"none"},"transform":"matrix(1,0,0,1,7343,45)"},{"parent":"main","new":"path","id":"_10689","d":"M368,1 L368,5","style":{"stroke":"rgb(0,0,255)","fill":"none"},"transform":"matrix(1,0,0,1,7343,45)"},{"parent":"main","new":"path","id":"_10690","d":"M7715.60009765625,39 L7725.39990234375,39","style":{"stroke-width":0.4},"transform":"matrix(1,0,0,1,0,0)"},{"parent":"main","new":"path","id":"_10691","d":"M7715.60009765625,33 L7725.39990234375,33","style":{"stroke-width":0.4},"transform":"matrix(1,0,0,1,0,0)"},{"parent":"main","new":"text","id":"_10692","x":0,"y":0,"child":"","style":{"fill":"rgb(0,0,0)","font-family":"Bravura","font-size":22},"transform":"matrix(1,0,0,1,7717,33)"},{"parent":"main","new":"text","id":"_10693","x":0,"y":0,"child":"","style":{"fill":"rgb(0,0,0)","font-family":"Bravura","font-size":24},"transform":"matrix(1,0,0,1,7711.5556640625,33)"},{"parent":"main","new":"path","id":"_10694","d":"M5,3 L393,3","style":{"stroke-width":2,"stroke":"rgb(0,0,255)","fill":"none"},"transform":"matrix(1,0,0,1,7719,30)"},{"parent":"main","new":"path","id":"_12329","d":"M393,1 L393,5","style":{"stroke":"rgb(0,0,255)","fill":"none"},"transform":"matrix(1,0,0,1,7719,30)"},{"parent":"main","new":"path","id":"_12330","d":"M8915.599609375,39 L8925.400390625,39","style":{"stroke-width":0.4},"transform":"matrix(1,0,0,1,0,0)"},{"parent":"main","new":"path","id":"_12331","d":"M8915.599609375,33 L8925.400390625,33","style":{"stroke-width":0.4},"transform":"matrix(1,0,0,1,0,0)"},{"parent":"main","new":"text","id":"_12332","x":0,"y":0,"child":"","style":{"fill":"rgb(0,0,0)","font-family":"Bravura","font-size":22},"transform":"matrix(1,0,0,1,8917,30)"},{"parent":"main","new":"text","id":"_12333","x":0,"y":0,"child":"","style":{"fill":"rgb(0,0,0)","font-family":"Bravura","font-size":24},"transform":"matrix(1,0,0,1,8914,87)"},{"parent":"main","new":"path","id":"_12334","d":"M5,3 L26.333001,3","style":{"stroke-width":2,"stroke":"rgb(0,0,255)","fill":"none"},"transform":"matrix(1,0,0,1,8919,27)"},{"parent":"main","new":"path","id":"_12335","d":"M26.333001,1 L26.333001,5","style":{"stroke":"rgb(0,0,255)","fill":"none"},"transform":"matrix(1,0,0,1,8919,27)"},{"parent":"main","new":"text","id":"_12336","x":0,"y":0,"child":"","style":{"fill":"rgb(0,0,0)","font-family":"Bravura","font-size":22},"transform":"matrix(1,0,0,1,8949,51)"},{"parent":"main","new":"path","id":"_12337","d":"M5,3 L459.666002,3","style":{"stroke-width":2,"stroke":"rgb(0,0,255)","fill":"none"},"transform":"matrix(1,0,0,1,8951,48)"},{"parent":"main","new":"path","id":"_14459","d":"M459.666002,1 L459.666002,5","style":{"stroke":"rgb(0,0,255)","fill":"none"},"transform":"matrix(1,0,0,1,8951,48)"},{"parent":"main","new":"text","id":"_14460","x":0,"y":0,"child":"","style":{"fill":"rgb(0,0,0)","font-family":"Bravura","font-size":22},"transform":"matrix(1,0,0,1,10917,42)"},{"parent":"main","new":"text","id":"_14461","x":0,"y":0,"child":"","style":{"fill":"rgb(0,0,0)","font-family":"Bravura","font-size":24},"transform":"matrix(1,0,0,1,10914,87)"},{"parent":"main","new":"path","id":"_14462","d":"M5,3 L393,3","style":{"stroke-width":2,"stroke":"rgb(0,0,255)","fill":"none"},"transform":"matrix(1,0,0,1,10919,39)"},{"parent":"main","new":"path","id":"_14969","d":"M393,1 L393,5","style":{"stroke":"rgb(0,0,255)","fill":"none"},"transform":"matrix(1,0,0,1,10919,39)"},{"parent":"main","new":"text","id":"_14970","x":0,"y":0,"child":"","style":{"fill":"rgb(0,0,0)","font-family":"Bravura","font-size":22},"transform":"matrix(1,0,0,1,11341,45)"},{"parent":"main","new":"text","id":"_14971","x":0,"y":0,"child":"","style":{"fill":"rgb(0,0,0)","font-family":"Bravura","font-size":24},"transform":"matrix(1,0,0,1,11338,87)"},{"parent":"main","new":"path","id":"_14972","d":"M5,3 L468,3","style":{"stroke-width":2,"stroke":"rgb(0,0,255)","fill":"none"},"transform":"matrix(1,0,0,1,11343,42)"},{"parent":"main","new":"path","id":"_15947","d":"M468,1 L468,5","style":{"stroke":"rgb(0,0,255)","fill":"none"},"transform":"matrix(1,0,0,1,11343,42)"},{"parent":"main","new":"path","id":"_15948","d":"M12115.599609375,39 L12125.400390625,39","style":{"stroke-width":0.4},"transform":"matrix(1,0,0,1,0,0)"},{"parent":"main","new":"text","id":"_15949","x":0,"y":0,"child":"","style":{"fill":"rgb(0,0,0)","font-family":"Bravura","font-size":22},"transform":"matrix(1,0,0,1,12117,39)"},{"parent":"main","new":"text","id":"_15950","x":0,"y":0,"child":"","style":{"fill":"rgb(0,0,0)","font-family":"Bravura","font-size":24},"transform":"matrix(1,0,0,1,12114,87)"},{"parent":"main","new":"path","id":"_15951","d":"M5,3 L393,3","style":{"stroke-width":2,"stroke":"rgb(0,0,255)","fill":"none"},"transform":"matrix(1,0,0,1,12119,36)"},{"parent":"main","new":"path","id":"_16994","d":"M393,1 L393,5","style":{"stroke":"rgb(0,0,255)","fill":"none"},"transform":"matrix(1,0,0,1,12119,36)"},{"parent":"main","new":"text","id":"_16995","x":0,"y":0,"child":"","style":{"fill":"rgb(0,0,0)","font-family":"Bravura","font-size":22},"transform":"matrix(1,0,0,1,12941,48)"},{"parent":"main","new":"text","id":"_16996","x":0,"y":0,"child":"","style":{"fill":"rgb(0,0,0)","font-family":"Bravura","font-size":24},"transform":"matrix(1,0,0,1,12938,87)"},{"parent":"main","new":"path","id":"_16997","d":"M5,3 L368,3","style":{"stroke-width":2,"stroke":"rgb(0,0,255)","fill":"none"},"transform":"matrix(1,0,0,1,12943,45)"},{"parent":"main","new":"path","id":"_17518","d":"M368,1 L368,5","style":{"stroke":"rgb(0,0,255)","fill":"none"},"transform":"matrix(1,0,0,1,12943,45)"},{"parent":"main","new":"path","id":"_17519","d":"M13315.599609375,39 L13325.400390625,39","style":{"stroke-width":0.4},"transform":"matrix(1,0,0,1,0,0)"},{"parent":"main","new":"path","id":"_17520","d":"M13315.599609375,33 L13325.400390625,33","style":{"stroke-width":0.4},"transform":"matrix(1,0,0,1,0,0)"},{"parent":"main","new":"text","id":"_17521","x":0,"y":0,"child":"","style":{"fill":"rgb(0,0,0)","font-family":"Bravura","font-size":22},"transform":"matrix(1,0,0,1,13317,33)"},{"parent":"main","new":"text","id":"_17522","x":0,"y":0,"child":"","style":{"fill":"rgb(0,0,0)","font-family":"Bravura","font-size":24},"transform":"matrix(1,0,0,1,13311.5556640625,33)"},{"parent":"main","new":"path","id":"_17523","d":"M5,3 L393,3","style":{"stroke-width":2,"stroke":"rgb(0,0,255)","fill":"none"},"transform":"matrix(1,0,0,1,13319,30)"},{"parent":"main","new":"path","id":"_19128","d":"M393,1 L393,5","style":{"stroke":"rgb(0,0,255)","fill":"none"},"transform":"matrix(1,0,0,1,13319,30)"},{"parent":"main","new":"path","id":"_19129","d":"M14515.599609375,39 L14525.400390625,39","style":{"stroke-width":0.4},"transform":"matrix(1,0,0,1,0,0)"},{"parent":"main","new":"path","id":"_19130","d":"M14515.599609375,33 L14525.400390625,33","style":{"stroke-width":0.4},"transform":"matrix(1,0,0,1,0,0)"},{"parent":"main","new":"path","id":"_19131","d":"M14515.599609375,27 L14525.400390625,27","style":{"stroke-width":0.4},"transform":"matrix(1,0,0,1,0,0)"},{"parent":"main","new":"text","id":"_19132","x":0,"y":0,"child":"","style":{"fill":"rgb(0,0,0)","font-family":"Bravura","font-size":22},"transform":"matrix(1,0,0,1,14517,27)"},{"parent":"main","new":"text","id":"_19133","x":0,"y":0,"child":"","style":{"fill":"rgb(0,0,0)","font-family":"Bravura","font-size":24},"transform":"matrix(1,0,0,1,14511.5556640625,27)"},{"parent":"main","new":"text","id":"_19134","x":0,"y":0,"child":"","style":{"fill":"rgb(0,0,0)","font-family":"Bravura","font-size":24},"transform":"matrix(1,0,0,1,14514,87)"},{"parent":"main","new":"path","id":"_19135","d":"M5,3 L26.333001,3","style":{"stroke-width":2,"stroke":"rgb(0,0,255)","fill":"none"},"transform":"matrix(1,0,0,1,14519,24)"},{"parent":"main","new":"path","id":"_19136","d":"M26.333001,1 L26.333001,5","style":{"stroke":"rgb(0,0,255)","fill":"none"},"transform":"matrix(1,0,0,1,14519,24)"},{"parent":"main","new":"text","id":"_19137","x":0,"y":0,"child":"","style":{"fill":"rgb(0,0,0)","font-family":"Bravura","font-size":22},"transform":"matrix(1,0,0,1,14549,51)"},{"parent":"main","new":"path","id":"_19138","d":"M5,3 L459.666002,3","style":{"stroke-width":2,"stroke":"rgb(0,0,255)","fill":"none"},"transform":"matrix(1,0,0,1,14551,48)"},{"parent":"main","new":"path","id":"_21002","d":"M459.666002,1 L459.666002,5","style":{"stroke":"rgb(0,0,255)","fill":"none"},"transform":"matrix(1,0,0,1,14551,48)"},{"parent":"main","new":"path","id":"_21003","d":"M15715.599609375,39 L15725.400390625,39","style":{"stroke-width":0.4},"transform":"matrix(1,0,0,1,0,0)"},{"parent":"main","new":"path","id":"_21004","d":"M15715.599609375,33 L15725.400390625,33","style":{"stroke-width":0.4},"transform":"matrix(1,0,0,1,0,0)"},{"parent":"main","new":"text","id":"_21005","x":0,"y":0,"child":"","style":{"fill":"rgb(0,0,0)","font-family":"Bravura","font-size":22},"transform":"matrix(1,0,0,1,15717,33)"},{"parent":"main","new":"text","id":"_21006","x":0,"y":31,"child":"","style":{"stroke":"rgb(0,0,0)","fill":"rgb(0,0,0)","stroke-width":0,"font-family":"Aloisen New","font-size":24,"font-style":["normal","normal"]},"transform":"matrix(1,0,0,1,15698.25,66.25)"},{"parent":"main","new":"path","id":"_21007","d":"M5,3 L393,3","style":{"stroke-width":2,"stroke":"rgb(0,0,255)","fill":"none"},"transform":"matrix(1,0,0,1,15719,30)"},{"parent":"main","new":"path","id":"_21663","d":"M393,1 L393,5","style":{"stroke":"rgb(0,0,255)","fill":"none"},"transform":"matrix(1,0,0,1,15719,30)"},{"parent":"main","new":"path","id":"_21664","d":"M0,0L100,7.5,0,15","style":{"fill":"none","stroke-width":0.6},"transform":"matrix(-3.02,0,0,1,16025,99)"},{"parent":"main","new":"text","id":"_21665","x":0,"y":0,"child":"","style":{"fill":"rgb(0,0,0)","font-family":"Bravura","font-size":22},"transform":"matrix(1,0,0,1,16144,60)"},{"parent":"main","new":"text","id":"_21666","x":0,"y":0,"child":"","style":{"fill":"rgb(0,0,0)","font-family":"Bravura","font-size":24},"transform":"matrix(1,0,0,1,16136.5556640625,60)"},{"parent":"main","new":"text","id":"_21667","x":0,"y":0,"child":"","style":{"fill":"rgb(0,0,0)","font-family":"Bravura","font-size":24},"transform":"matrix(1,0,0,1,16141,87)"},{"parent":"main","new":"path","id":"_21668","d":"M5,3 L468,3","style":{"stroke-width":2,"stroke":"rgb(0,0,255)","fill":"none"},"transform":"matrix(1,0,0,1,16146,57)"},{"parent":"main","new":"path","id":"_22855","d":"M468,1 L468,5","style":{"stroke":"rgb(0,0,255)","fill":"none"},"transform":"matrix(1,0,0,1,16146,57)"},{"parent":"main","new":"path","id":"_22856","d":"M16915.599609375,39 L16925.400390625,39","style":{"stroke-width":0.4},"transform":"matrix(1,0,0,1,0,0)"},{"parent":"main","new":"path","id":"_22857","d":"M16915.599609375,33 L16925.400390625,33","style":{"stroke-width":0.4},"transform":"matrix(1,0,0,1,0,0)"},{"parent":"main","new":"text","id":"_22858","x":0,"y":0,"child":"","style":{"fill":"rgb(0,0,0)","font-family":"Bravura","font-size":22},"transform":"matrix(1,0,0,1,16917,30)"},{"parent":"main","new":"text","id":"_22859","x":0,"y":0,"child":"","style":{"fill":"rgb(0,0,0)","font-family":"Bravura","font-size":24},"transform":"matrix(1,0,0,1,16914,87)"},{"parent":"main","new":"path","id":"_22860","d":"M5,3 L393,3","style":{"stroke-width":2,"stroke":"rgb(0,0,255)","fill":"none"},"transform":"matrix(1,0,0,1,16919,27)"},{"parent":"main","new":"path","id":"_23971","d":"M393,1 L393,5","style":{"stroke":"rgb(0,0,255)","fill":"none"},"transform":"matrix(1,0,0,1,16919,27)"},{"parent":"main","new":"path","id":"_23972","d":"M0,45 L18000,45,M0,51 L18000,51,M0,57 L18000,57,M0,63 L18000,63,M0,69 L18000,69,","style":{"stroke-width":0.4},"transform":"matrix(1,0,0,1,0,0)"}]},{"new":"g","id":"scoreGroup"},{"new":"g","id":"overlay"},{"parent":"overlay","new":"line","id":"playhead","x1":250,"x2":250,"y1":0,"y2":720,"style":{"stroke":"red","stroke-width":3,"stroke-opacity":0.5}},{"parent":"overlay","new":"line","id":"miniplayhead","x1":320,"x2":320,"y1":4,"y2":54,"style":{"stroke":"blue","stroke-width":3,"stroke-opacity":0.5}},{"parent":"overlay","new":"text","id":"timecount","x":195,"y":35},{"id":"score","parent":"scoreGroup","new":"use","href":"#defscore","x":250,"y":100},{"new":"g","id":"overlay_clef","transform":"matrix(1.5, 0, 0, 1.5, 0, 100)","child":{"id":"clef","parent":"overlay","new":"text","x":60,"y":51,"child":"","style":{"font-family":"Bravura","font-size":22},"transform":"matrix(1,0,0,1,0,0)"}},{"new":"g","id":"overlay_title","transform":"translate(320, 90)","child":{"id":"title","new":"text","x":0,"y":0,"child":"Georg Hajdu: Cycling 144","style":{"font-family":"Times New Roman","font-size":30},"transform":"matrix(1,0,0,1,0,0)"}},{"id":"mini","parent":"scoreGroup","new":"use","href":"#defscore","y":12,"x":12397.714285714286,"transform":"scale(0.025811209439528023, 0.3333333333333333)","class":"noclick"},{"new":"text","id":"playerID","x":10,"y":90,"text":"92 violoncello"},{"parent":"overlay","id":"scrollbar","new":"rect","x":320,"y":4,"height":50,"width":700,"fill":"rgba(0,0,255,0.25)","onmousemove":"\n                    event.preventDefault();\n                    let x = event.clientX;\n                    if(event.buttons == 1){\n                        let r = ( ( x - 320 ) / 700) * 180.8000030517578;\n                        drawsocket.input({\n                            key: 'tween',\n                            val: [{\n                                id: 'score-anim',\n                                cmd: 'pause',\n                                time: r \n                            }, {\n                                id: 'miniscore-anim',\n                                cmd: 'pause',\n                                time: r\n                            }]\n                        });\n                        let uiTxt = document.getElementById('userinput');\n                        uiTxt.value = r;\n                        let button = document.getElementById('playbutton');\n                        if( button.classList.contains('ready') )\n                            button.classList.remove('ready');\n    \n                    }","ontouchmove":"\n                    event.preventDefault();\n                    let x = event.pageX;\n                    let r = ((x-320) / 700) * 180.8000030517578;\n                    drawsocket.input({\n                        key: 'tween',\n                        val: [{\n                            id: 'score-anim',\n                            cmd: 'pause',\n                            time: r \n                        }, {\n                            id: 'miniscore-anim',\n                            cmd: 'pause',\n                            time: r\n                        }]\n                    });\n                    let uiTxt = document.getElementById('userinput');\n                    uiTxt.value = r;\n                    "}]},{"key":"tween","val":[{"id":"score-anim","target":"#score","dur":180.8000030517578,"vars":{"x":-27120,"ease":"linear","paused":"true","onUpdate":{"function":" \n  if( this.time() % 1\t< 0.05){\n    let text = document.getElementById('timecount');\n    text.innerHTML = Math.floor( this.time() );\n  }\n"}}},{"id":"miniscore-anim","target":"#miniplayhead","dur":180.8000030517578,"vars":{"x":"+=700","ease":"linear","paused":"true"}}]}]}